Workbook
Name cad_Fontes: Cadastros!$E$2:$E$4
Name cad_Inst: Cadastros!$A$2:$A$200
Name cad_Meses: Cadastros!$G$2:$G$500
Name cad_Mod: Cadastros!$C$2:$C$200
Name col_Ap: Base!$P$2:$P$50000
Name col_Data: Base!$A$2:$A$50000
Name col_Fonte: Base!$C$2:$C$50000
Name col_ID: Base!$B$2:$B$50000
Name col_Inst: Base!$E$2:$E$50000
Name col_IOFR: Base!$V$2:$V$50000
Name col_IRP: Base!$W$2:$W$50000
Name col_IRR: Base!$U$2:$U$50000
Name col_Jur: Base!$R$2:$R$50000
Name col_Mod: Base!$F$2:$F$50000
Name col_Mov: Base!$BA$2:$BA$50000
Name col_Rend: Base!$S$2:$S$50000
Name col_Res: Base!$Q$2:$Q$50000
Name col_SA: Base!$O$2:$O$50000
Name col_SF: Base!$T$2:$T$50000
Name col_SMed: Base!$BB$2:$BB$50000
Name ind_CDI: Indicadores!$B$2:$B$500
Name ind_IPCA: Indicadores!$C$2:$C$500
Name ind_Mes: Indicadores!$A$2:$A$500
Name ind_Orig: Indicadores!$D$2:$D$500
Name LimiteConc: Config!$B$4
Name MesAnt: Config!$B$9
Name MesRef: Config!$B$3
Name MetaCDI: Config!$B$5
Name PastaPDF: Config!$B$7
Name QtdAlertas: Conferencias!$C$4
Name QtdErros: Conferencias!$C$3
Name StatusRelatorio: Config!$B$8
Name TolContinuidade: Config!$B$6

Sheet LEIAME
A1: Gerador de Relatório Executivo de Carteira de Renda Fixa — ARQUIVO DE EXEMPLO
A2: Todos os dados deste arquivo são FICTÍCIOS e servem apenas para demonstração.
A4: Como usar:
A5: 1. Salve este arquivo como 'Pasta de Trabalho Habilitada para Macro (*.xlsm)'.
A6: 2. Abra o editor VBA (Alt+F11), selecione ESTE arquivo no painel e importe os 3 módulos da pasta /vba.
A7: 3. Execute a macro CriarBotoes (Alt+F8) uma única vez para criar os botões na aba Resumo.
A8: 4. Clique em 'Importar mês' e escolha exemplos/planilha_mensal_2025-04_data_fim_de_semana.xlsx.
A9: 5. Veja a aba Conferencias: deve aparecer ALERTA de data-base em fim de semana (não bloqueia o PDF).
A10: 6. Importe exemplos/planilha_mensal_2025-05_com_erro.xlsx: deve aparecer ERRO (instituição não cadastrada).
A11: 7. Clique em 'Gerar PDF'. Com ERRO, a macro só permite gerar a versão PRELIMINAR.
A13: Células com fundo amarelo e fonte azul são entradas manuais. As demais são fórmulas: não sobrescreva.
A14: A macro NÃO salva a base automaticamente: revise e salve manualmente após cada importação.

Sheet Resumo
A1: Relatório Executivo de Investimentos
A2: ="Mês de referência: "&CHOOSE(MONTH(MesRef),"janeiro","fevereiro","março","abril","maio","junho","julho","agosto","setembro","outubro","novembro","dezembro")&"/"&YEAR(MesRef)&" | Dados fictícios de demonstração" -> Mês de referência: março/2025 | Dados fictícios de demonstração
A3: =IF(StatusRelatorio="PRELIMINAR","VERSÃO PRELIMINAR — há conferências com ERRO","")
A5: 1. Resultado do mês
A6: Indicador | B6: Mês de referência | C6: Mês anterior | D6: Variação
A7: Saldo final total | B7: =SUMIFS(col_SF,col_Data,MesRef) -> 42617210 | C7: =SUMIFS(col_SF,col_Data,MesAnt) -> 43347596 | D7: =B7-C7 -> -730386.18
A8: Aplicações | B8: =SUMIFS(col_Ap,col_Data,MesRef) -> 23401.98 | C8: =SUMIFS(col_Ap,col_Data,MesAnt) -> 610878.52 | D8: =B8-C8 -> -587476.54
A9: Resgates | B9: =SUMIFS(col_Res,col_Data,MesRef) -> 1102210.5 | C9: =SUMIFS(col_Res,col_Data,MesAnt) -> 742352.27 | D9: =B9-C9 -> 359858.26
A10: Juros recebidos | B10: =SUMIFS(col_Jur,col_Data,MesRef) -> 0 | C10: =SUMIFS(col_Jur,col_Data,MesAnt) -> 0 | D10: =B10-C10 -> 0
A11: Rendimento bruto | B11: =SUMIFS(col_Rend,col_Data,MesRef) -> 359745.59 | C11: =SUMIFS(col_Rend,col_Data,MesAnt) -> 341221.07 | D11: =B11-C11 -> 18524.52
A12: IR/IOF retido na cota | B12: =SUMIFS(col_IRR,col_Data,MesRef)+SUMIFS(col_IOFR,col_Data,MesRef) -> 11323.22 | C12: =SUMIFS(col_IRR,col_Data,MesAnt)+SUMIFS(col_IOFR,col_Data,MesAnt) -> 10149.92 | D12: =B12-C12 -> 1173.3
A13: IR provisionado | B13: =SUMIFS(col_IRP,col_Data,MesRef) -> 28174.91 | C13: =SUMIFS(col_IRP,col_Data,MesAnt) -> 27916.47 | D13: =B13-C13 -> 258.44
A14: Saldo médio (média simples) | B14: =SUMIFS(col_SMed,col_Data,MesRef) -> 42982403 | C14: =SUMIFS(col_SMed,col_Data,MesAnt) -> 43247798 | D14: =B14-C14 -> -265394.39
A15: Rentabilidade do mês | B15: =IFERROR(B11/B14,0) -> 0.0083696016 | C15: =IFERROR(C11/C14,0) -> 0.0078899063 | D15: =B15-C15 -> 0.0004796953
A16: CDI do mês | B16: =IFERROR(INDEX(ind_CDI,MATCH(MesRef,ind_Mes,0)),0) -> 0.0097 | C16: =IFERROR(INDEX(ind_CDI,MATCH(MesAnt,ind_Mes,0)),0) -> 0.0088 | D16: =B16-C16 -> 0.0009
A17: Rentabilidade em % do CDI | B17: =IFERROR(B15/B16,0) -> 0.86284552 | C17: =IFERROR(C15/C16,0) -> 0.89658026 | D17: =B17-C17 -> -0.033734735
A18: Meta (% do CDI) | B18: =MetaCDI -> 1 | C18: =MetaCDI -> 1 | D18: =B18-C18 -> 0
A19: Situação da meta | B19: =IF(B17>=B18,"Atingida","Não atingida") -> Não atingida | C19: =IF(C16=0,"-",IF(C17>=C18,"Atingida","Não atingida")) -> Não atingida
A21: 2. Variação do rendimento: efeito volume × efeito taxa
A22: Variação do rendimento bruto | B22: =B11-C11 -> 18524.52
A23: Efeito volume = (saldo médio atual − anterior) × taxa anterior | B23: =IFERROR((B14-C14)*C15,0) -> -2093.9369
A24: Efeito taxa = variação − efeito volume | B24: =B22-B23 -> 20618.457
A26: 3. Distribuição por fonte de recursos
A27: Fonte | B27: Saldo final | C27: Participação | D27: Rendimento bruto
A28: =Cadastros!E2 -> Recursos Proprios | B28: =SUMIFS(col_SF,col_Data,MesRef,col_Fonte,A28) -> 21296607 | C28: =IFERROR(B28/$B$7,0) -> 0.49971846 | D28: =SUMIFS(col_Rend,col_Data,MesRef,col_Fonte,A28) -> 190325.32
A29: =Cadastros!E3 -> Recursos de Terceiros | B29: =SUMIFS(col_SF,col_Data,MesRef,col_Fonte,A29) -> 9993010.5 | C29: =IFERROR(B29/$B$7,0) -> 0.23448298 | D29: =SUMIFS(col_Rend,col_Data,MesRef,col_Fonte,A29) -> 76122.12
A30: =Cadastros!E4 -> Financiamento de Base | B30: =SUMIFS(col_SF,col_Data,MesRef,col_Fonte,A30) -> 11327593 | C30: =IFERROR(B30/$B$7,0) -> 0.26579856 | D30: =SUMIFS(col_Rend,col_Data,MesRef,col_Fonte,A30) -> 93298.15
A31: Total | B31: =SUM(B28:B30) -> 42617210 | C31: =SUM(C28:C30) -> 1 | D31: =SUM(D28:D30) -> 359745.59
A33: 4. Concentração por instituição
A34: Instituição | B34: Saldo final | C34: Participação | D34: Limite | E34: Margem | F34: Situação
A35: =IF(Cadastros!A2="","",Cadastros!A2) -> Banco Alfa | B35: =IF(A35="","",SUMIFS(col_SF,col_Data,MesRef,col_Inst,A35)) -> 14664011 | C35: =IF(A35="","",IFERROR(B35/$B$7,0)) -> 0.3440866 | D35: =IF(A35="","",LimiteConc) -> 0.3 | E35: =IF(A35="","",D35-C35) -> -0.044086597 | F35: =IF(A35="","",IF(C35>D35,"Atenção","Conforme")) -> Atenção
A36: =IF(Cadastros!A3="","",Cadastros!A3) -> Banco Beta | B36: =IF(A36="","",SUMIFS(col_SF,col_Data,MesRef,col_Inst,A36)) -> 9329108.5 | C36: =IF(A36="","",IFERROR(B36/$B$7,0)) -> 0.21890472 | D36: =IF(A36="","",LimiteConc) -> 0.3 | E36: =IF(A36="","",D36-C36) -> 0.08109528 | F36: =IF(A36="","",IF(C36>D36,"Atenção","Conforme")) -> Conforme
A37: =IF(Cadastros!A4="","",Cadastros!A4) -> Banco Gama | B37: =IF(A37="","",SUMIFS(col_SF,col_Data,MesRef,col_Inst,A37)) -> 3020589.4 | C37: =IF(A37="","",IFERROR(B37/$B$7,0)) -> 0.070877221 | D37: =IF(A37="","",LimiteConc) -> 0.3 | E37: =IF(A37="","",D37-C37) -> 0.22912278 | F37: =IF(A37="","",IF(C37>D37,"Atenção","Conforme")) -> Conforme
A38: =IF(Cadastros!A5="","",Cadastros!A5) -> Cooperativa Delta | B38: =IF(A38="","",SUMIFS(col_SF,col_Data,MesRef,col_Inst,A38)) -> 6320893.6 | C38: =IF(A38="","",IFERROR(B38/$B$7,0)) -> 0.14831786 | D38: =IF(A38="","",LimiteConc) -> 0.3 | E38: =IF(A38="","",D38-C38) -> 0.15168214 | F38: =IF(A38="","",IF(C38>D38,"Atenção","Conforme")) -> Conforme
A39: =IF(Cadastros!A6="","",Cadastros!A6) -> Banco Epsilon | B39: =IF(A39="","",SUMIFS(col_SF,col_Data,MesRef,col_Inst,A39)) -> 9282607.9 | C39: =IF(A39="","",IFERROR(B39/$B$7,0)) -> 0.2178136 | D39: =IF(A39="","",LimiteConc) -> 0.3 | E39: =IF(A39="","",D39-C39) -> 0.082186402 | F39: =IF(A39="","",IF(C39>D39,"Atenção","Conforme")) -> Conforme
A40: =IF(Cadastros!A7="","",Cadastros!A7) | B40: =IF(A40="","",SUMIFS(col_SF,col_Data,MesRef,col_Inst,A40)) | C40: =IF(A40="","",IFERROR(B40/$B$7,0)) | D40: =IF(A40="","",LimiteConc) | E40: =IF(A40="","",D40-C40) | F40: =IF(A40="","",IF(C40>D40,"Atenção","Conforme"))
A41: =IF(Cadastros!A8="","",Cadastros!A8) | B41: =IF(A41="","",SUMIFS(col_SF,col_Data,MesRef,col_Inst,A41)) | C41: =IF(A41="","",IFERROR(B41/$B$7,0)) | D41: =IF(A41="","",LimiteConc) | E41: =IF(A41="","",D41-C41) | F41: =IF(A41="","",IF(C41>D41,"Atenção","Conforme"))
A42: =IF(Cadastros!A9="","",Cadastros!A9) | B42: =IF(A42="","",SUMIFS(col_SF,col_Data,MesRef,col_Inst,A42)) | C42: =IF(A42="","",IFERROR(B42/$B$7,0)) | D42: =IF(A42="","",LimiteConc) | E42: =IF(A42="","",D42-C42) | F42: =IF(A42="","",IF(C42>D42,"Atenção","Conforme"))
A43: =IF(Cadastros!A10="","",Cadastros!A10) | B43: =IF(A43="","",SUMIFS(col_SF,col_Data,MesRef,col_Inst,A43)) | C43: =IF(A43="","",IFERROR(B43/$B$7,0)) | D43: =IF(A43="","",LimiteConc) | E43: =IF(A43="","",D43-C43) | F43: =IF(A43="","",IF(C43>D43,"Atenção","Conforme"))
A44: =IF(Cadastros!A11="","",Cadastros!A11) | B44: =IF(A44="","",SUMIFS(col_SF,col_Data,MesRef,col_Inst,A44)) | C44: =IF(A44="","",IFERROR(B44/$B$7,0)) | D44: =IF(A44="","",LimiteConc) | E44: =IF(A44="","",D44-C44) | F44: =IF(A44="","",IF(C44>D44,"Atenção","Conforme"))
A45: “Atenção” indica participação acima do limite parametrizado; não equivale a não conformidade confirmada.
A47: 5. Distribuição por modalidade
A48: Modalidade | B48: Saldo final | C48: Participação
A49: =IF(Cadastros!C2="","",Cadastros!C2) -> CDB | B49: =IF(A49="","",SUMIFS(col_SF,col_Data,MesRef,col_Mod,A49)) -> 4538603.1 | C49: =IF(A49="","",IFERROR(B49/$B$7,0)) -> 0.10649695
A50: =IF(Cadastros!C3="","",Cadastros!C3) -> LCA | B50: =IF(A50="","",SUMIFS(col_SF,col_Data,MesRef,col_Mod,A50)) -> 8856888.7 | C50: =IF(A50="","",IFERROR(B50/$B$7,0)) -> 0.20782423
A51: =IF(Cadastros!C4="","",Cadastros!C4) -> LCI | B51: =IF(A51="","",SUMIFS(col_SF,col_Data,MesRef,col_Mod,A51)) -> 1977817.2 | C51: =IF(A51="","",IFERROR(B51/$B$7,0)) -> 0.046408886
A52: =IF(Cadastros!C5="","",Cadastros!C5) -> Fundo DI | B52: =IF(A52="","",SUMIFS(col_SF,col_Data,MesRef,col_Mod,A52)) -> 7125552.6 | C52: =IF(A52="","",IFERROR(B52/$B$7,0)) -> 0.16719895
A53: =IF(Cadastros!C6="","",Cadastros!C6) -> Fundo Aplic. Automatica | B53: =IF(A53="","",SUMIFS(col_SF,col_Data,MesRef,col_Mod,A53)) -> 3430018.3 | C53: =IF(A53="","",IFERROR(B53/$B$7,0)) -> 0.080484346
A54: =IF(Cadastros!C7="","",Cadastros!C7) -> Tesouro Selic | B54: =IF(A54="","",SUMIFS(col_SF,col_Data,MesRef,col_Mod,A54)) -> 9871253.9 | C54: =IF(A54="","",IFERROR(B54/$B$7,0)) -> 0.231626
A55: =IF(Cadastros!C8="","",Cadastros!C8) -> Tesouro IPCA+ | B55: =IF(A55="","",SUMIFS(col_SF,col_Data,MesRef,col_Mod,A55)) -> 2189016.7 | C55: =IF(A55="","",IFERROR(B55/$B$7,0)) -> 0.051364618
A56: =IF(Cadastros!C9="","",Cadastros!C9) -> Compromissada | B56: =IF(A56="","",SUMIFS(col_SF,col_Data,MesRef,col_Mod,A56)) -> 4628059.7 | C56: =IF(A56="","",IFERROR(B56/$B$7,0)) -> 0.10859603
A57: =IF(Cadastros!C10="","",Cadastros!C10) | B57: =IF(A57="","",SUMIFS(col_SF,col_Data,MesRef,col_Mod,A57)) | C57: =IF(A57="","",IFERROR(B57/$B$7,0))
A58: =IF(Cadastros!C11="","",Cadastros!C11) | B58: =IF(A58="","",SUMIFS(col_SF,col_Data,MesRef,col_Mod,A58)) | C58: =IF(A58="","",IFERROR(B58/$B$7,0))
A60: 6. Pontos de atenção (gerados por fórmula)
A61: =IF(B17>=B18,"Meta atingida: ","Meta não atingida: ")&FIXED(B17*100,1)&"% do CDI (meta de "&FIXED(B18*100,0)&"%)." -> Meta não atingida: 86,3% do CDI (meta de 100%).
A62: ="Variação do rendimento: R$ "&FIXED(B22,2)&" (efeito volume R$ "&FIXED(B23,2)&"; efeito taxa R$ "&FIXED(B24,2)&")." -> Variação do rendimento: R$ 18.524,52 (efeito volume R$ -2.093,94; efeito taxa R$ 20.618,46).
A63: ="Instituições acima do limite de concentração: "&COUNTIF(F35:F44,"Atenção")&"." -> Instituições acima do limite de concentração: 1.
A64: ="Conferências: "&QtdErros&" erro(s) e "&QtdAlertas&" alerta(s). Detalhes na aba Conferencias." -> Conferências: 0 erro(s) e 0 alerta(s). Detalhes na aba Conferencias.
A66: 7. Comentário da analista (preenchimento manual)
A67: Digite aqui a análise do mês antes de gerar o PDF.
A73: Relatório gerado a partir de dados fictícios. Validação humana obrigatória antes de qualquer uso formal.

Sheet Conferencias
A1: Conferências de qualidade dos dados
B3: Quantidade de ERROS (bloqueiam o PDF final) | C3: =COUNTIF(E8:E30,"ERRO") -> 0
B4: Quantidade de ALERTAS (não bloqueiam) | C4: =COUNTIF(E8:E30,"ALERTA") -> 0
A7: # | B7: Conferência | C7: Resultado | D7: Critério | E7: Status
A8: 1 | B8: Mês de referência cadastrado | C8: =COUNTIF(cad_Meses,MesRef) -> 1 | D8: Deve ser ≥ 1 | E8: =IF(C8>=1,"OK","ERRO") -> OK
A9: 2 | B9: Linhas do mês na base | C9: =COUNTIF(col_Data,MesRef) -> 28 | D9: Deve ser > 0 | E9: =IF(C9>0,"OK","ERRO") -> OK
A10: 3 | B10: Linhas sem instituição ou modalidade | C10: =SUMPRODUCT((col_Data=MesRef)*(col_Inst=""))+SUMPRODUCT((col_Data=MesRef)*(col_Mod="")) -> 0 | D10: Deve ser 0 | E10: =IF(C10=0,"OK","ERRO") -> OK
A11: 4 | B11: Soma por fonte × total (diferença R$) | C11: =ROUND(SUMIFS(col_SF,col_Data,MesRef)-SUMPRODUCT(SUMIFS(col_SF,col_Data,MesRef,col_Fonte,cad_Fontes)),2) -> 0 | D11: Deve ser 0,00 | E11: =IF(ABS(C11)<0.01,"OK","ERRO") -> OK
A12: 5 | B12: Instituições não cadastradas (linhas) | C12: =SUMPRODUCT((col_Data=MesRef)*(COUNTIF(cad_Inst,col_Inst)=0)) -> 0 | D12: Deve ser 0 | E12: =IF(C12=0,"OK","ERRO") -> OK
A13: 6 | B13: Modalidades não cadastradas (linhas) | C13: =SUMPRODUCT((col_Data=MesRef)*(COUNTIF(cad_Mod,col_Mod)=0)) -> 0 | D13: Deve ser 0 | E13: =IF(C13=0,"OK","ERRO") -> OK
A14: 7 | B14: Linhas com movimentação que não fecha | C14: =SUMPRODUCT((col_Data=MesRef)*(ABS(col_Mov)>0.01)) -> 0 | D14: Deve ser 0 (tolerância R$ 0,01) | E14: =IF(C14=0,"OK","ERRO") -> OK
A15: 8 | B15: Continuidade do saldo (diferença R$) | C15: =IF(COUNTIF(col_Data,MesAnt)=0,"sem mês ant.",ROUND(SUMIFS(col_SA,col_Data,MesRef)-SUMIFS(col_SF,col_Data,MesAnt),2)) -> 0 | D15: Até a tolerância da aba Config | E15: =IF(ISNUMBER(C15),IF(ABS(C15)<=TolContinuidade,"OK","ALERTA"),"ALERTA") -> OK
A16: 9 | B16: Data-base original em dia útil | C16: =IFERROR(INDEX(ind_Orig,MATCH(MesRef,ind_Mes,0)),"não localizada") -> 45747 | D16: Segunda a sexta (feriados não considerados) | E16: =IF(ISNUMBER(C16),IF(WEEKDAY(C16,2)<=5,"OK","ALERTA"),"ALERTA") -> OK
A17: 10 | B17: Aplicações com rendimento negativo | C17: =SUMPRODUCT((col_Data=MesRef)*(col_Rend<0)) -> 0 | D17: Esperado 0 | E17: =IF(C17=0,"OK","ALERTA") -> OK
A18: 11 | B18: Mês anterior disponível na base | C18: =COUNTIF(col_Data,MesAnt) -> 28 | D18: Deve ser > 0 | E18: =IF(C18>0,"OK","ALERTA") -> OK
A19: 12 | B19: CDI do mês disponível | C19: =IFERROR(INDEX(ind_CDI,MATCH(MesRef,ind_Mes,0)),"não localizado") -> 0.0097 | D19: Deve estar preenchido | E19: =IF(AND(ISNUMBER(C19),C19<>0),"OK","ERRO") -> OK

Sheet Base
A1: Data_Base | B1: ID_Aplicacao | C1: Fonte | D1: Centro_Custo | E1: Instituicao | F1: Modalidade | G1: Produto | H1: Indexador | I1: Perc_CDI_Contratado | J1: Taxa_Prefixada | K1: Data_Aplicacao | L1: Data_Vencimento | M1: Liquidez | N1: Classificacao | O1: Saldo_Anterior | P1: Aplicacoes | Q1: Resgates | R1: Juros_Recebidos | S1: Rendimento_Bruto | T1: Saldo_Final | U1: IR_Retido | V1: IOF_Retido | W1: IR_Provisionado | X1: IOF_Provisionado | Y1: Saldo_Liquido | Z1: Rentab_Mes | AA1: Rentab_Perc_CDI | AB1: Rentab_Ano | AC1: Rentab_12m | AD1: CDI_Mes | AE1: CDI_Ano | AF1: CDI_12m | AG1: IPCA_Mes | AH1: Dias_Uteis_Mes | AI1: Prazo_Dias | AJ1: Faixa_Vencimento | AK1: Saldo_Liquido_de_IR | AL1: Aliquota_IR | AM1: Isento_IR | AN1: Garantia_FGC | AO1: Rating_Emissor | AP1: Emissor | AQ1: Custodiante | AR1: Conta_Referencia | AS1: Tipo_Resgate | AT1: Carencia_Dias | AU1: Enquadramento | AV1: Observacao | AW1: Area_Responsavel | AX1: Data_Atualizacao | AY1: Status | AZ1: Chave_Unica | BA1: Mov_Diferenca | BB1: Saldo_Medio
A2: 45688 | B2: APL-001 | C2: Financiamento de Base | D2: CC-002 | E2: Banco Alfa | F2: LCA | G2: LCA Banco Alfa | H2: CDI | I2: 0.9274 | K2: 45635 | L2: 46117 | M2: No vencimento | N2: Longo prazo | O2: 2235839.9 | P2: 0 | Q2: 0 | R2: 0 | S2: 19698.42 | T2: 2255538.4 | U2: 0 | V2: 0 | W2: 0 | X2: 0 | Y2: 2255538.4 | Z2: 0.00881 | AA2: 0.9274 | AD2: 0.0095 | AG2: 0.003 | AH2: 22 | AI2: 429 | AJ2: Acima de 360 dias | AK2: N | AL2: 0 | AM2: S | AN2: S | AO2: AAA | AP2: Banco Alfa | AQ2: Custodiante Ficticio | AR2: CT-001 | AS2: No vencimento | AT2: 0 | AU2: Autorizado | AW2: Financeiro | AX2: 45688 | AY2: Ativa | AZ2: APL-001-202501 | BA2: =ROUND(T2-(O2+P2-Q2-R2+S2-IF(AK2="S",U2+V2,0)),2) -> 0 | BB2: =(O2+T2)/2 -> 2245689.1
A3: 45688 | B3: APL-002 | C3: Recursos Proprios | D3: CC-009 | E3: Banco Epsilon | F3: LCA | G3: LCA Banco Epsilon | H3: CDI | I3: 0.9221 | K3: 45475 | L3: 45695 | M3: No vencimento | N3: Curto prazo | O3: 1425050.4 | P3: 0 | Q3: 0 | R3: 0 | S3: 12483.37 | T3: 1437533.8 | U3: 0 | V3: 0 | W3: 0 | X3: 0 | Y3: 1437533.8 | Z3: 0.00876 | AA3: 0.9221 | AD3: 0.0095 | AG3: 0.003 | AH3: 22 | AI3: 7 | AJ3: Ate 90 dias | AK3: N | AL3: 0 | AM3: S | AN3: S | AO3: AA | AP3: Banco Epsilon | AQ3: Custodiante Ficticio | AR3: CT-002 | AS3: No vencimento | AT3: 0 | AU3: Autorizado | AW3: Financeiro | AX3: 45688 | AY3: Ativa | AZ3: APL-002-202501 | BA3: =ROUND(T3-(O3+P3-Q3-R3+S3-IF(AK3="S",U3+V3,0)),2) -> 0 | BB3: =(O3+T3)/2 -> 1431292.1
A4: 45688 | B4: APL-003 | C4: Recursos Proprios | D4: CC-007 | E4: Banco Beta | F4: Tesouro IPCA+ | G4: Tesouro IPCA+ Banco Beta | H4: IPCA | J4: 0.0048 | K4: 45523 | L4: 46412 | M4: No vencimento | N4: Longo prazo | O4: 430924.77 | P4: 0 | Q4: 195947.52 | R4: 8618.5 | S4: 2597.02 | T4: 228955.77 | U4: 0 | V4: 0 | W4: 389.55 | X4: 0 | Y4: 228566.22 | Z4: 0.006027 | AA4: 0.6344 | AD4: 0.0095 | AG4: 0.003 | AH4: 22 | AI4: 724 | AJ4: Acima de 360 dias | AK4: N | AL4: 0.15 | AM4: N | AN4: N | AO4: AA | AP4: Banco Beta | AQ4: Custodiante Ficticio | AR4: CT-003 | AS4: No vencimento | AT4: 0 | AU4: Autorizado | AW4: Financeiro | AX4: 45688 | AY4: Ativa | AZ4: APL-003-202501 | BA4: =ROUND(T4-(O4+P4-Q4-R4+S4-IF(AK4="S",U4+V4,0)),2) -> 0 | BB4: =(O4+T4)/2 -> 329940.27
A5: 45688 | B5: APL-004 | C5: Recursos de Terceiros | D5: CC-005 | E5: Banco Alfa | F5: Tesouro Selic | G5: Tesouro Selic Banco Alfa | H5: CDI | I5: 1.0061 | K5: 45335 | L5: 45836 | M5: No vencimento | N5: Curto prazo | O5: 1837842.9 | P5: 0 | Q5: 0 | R5: 0 | S5: 17566.01 | T5: 1855408.9 | U5: 0 | V5: 0 | W5: 2634.9 | X5: 0 | Y5: 1852774 | Z5: 0.009558 | AA5: 1.0061 | AD5: 0.0095 | AG5: 0.003 | AH5: 22 | AI5: 148 | AJ5: 91 a 360 dias | AK5: N | AL5: 0.15 | AM5: N | AN5: N | AO5: AAA | AP5: Banco Alfa | AQ5: Custodiante Ficticio | AR5: CT-004 | AS5: No vencimento | AT5: 0 | AU5: Autorizado | AW5: Financeiro | AX5: 45688 | AY5: Ativa | AZ5: APL-004-202501 | BA5: =ROUND(T5-(O5+P5-Q5-R5+S5-IF(AK5="S",U5+V5,0)),2) -> 0 | BB5: =(O5+T5)/2 -> 1846625.9
A6: 45688 | B6: APL-005 | C6: Recursos de Terceiros | D6: CC-004 | E6: Cooperativa Delta | F6: LCA | G6: LCA Cooperativa Delta | H6: CDI | I6: 0.9293 | K6: 45340 | L6: 46711 | M6: No vencimento | N6: Longo prazo | O6: 162269.74 | P6: 0 | Q6: 36504.74 | R6: 0 | S6: 1271.44 | T6: 127036.44 | U6: 0 | V6: 0 | W6: 0 | X6: 0 | Y6: 127036.44 | Z6: 0.007835 | AA6: 0.8248 | AD6: 0.0095 | AG6: 0.003 | AH6: 22 | AI6: 1023 | AJ6: Acima de 360 dias | AK6: N | AL6: 0 | AM6: S | AN6: S | AO6: AAA | AP6: Cooperativa Delta | AQ6: Custodiante Ficticio | AR6: CT-005 | AS6: No vencimento | AT6: 0 | AU6: Autorizado | AW6: Financeiro | AX6: 45688 | AY6: Ativa | AZ6: APL-005-202501 | BA6: =ROUND(T6-(O6+P6-Q6-R6+S6-IF(AK6="S",U6+V6,0)),2) -> 0 | BB6: =(O6+T6)/2 -> 144653.09
A7: 45688 | B7: APL-006 | C7: Recursos Proprios | D7: CC-002 | E7: Banco Gama | F7: Fundo DI | G7: Fundo DI Banco Gama | H7: CDI | I7: 0.959 | K7: 45350 | M7: Diaria | N7: Curto prazo | O7: 1160855.2 | P7: 0 | Q7: 0 | R7: 0 | S7: 10575.97 | T7: 1169844.8 | U7: 1586.4 | V7: 0 | W7: 0 | X7: 0 | Y7: 1169844.8 | Z7: 0.00911 | AA7: 0.959 | AD7: 0.0095 | AG7: 0.003 | AH7: 22 | AJ7: Liquidez diaria | AK7: S | AL7: 0.15 | AM7: N | AN7: N | AO7: AA | AP7: Banco Gama | AQ7: Custodiante Ficticio | AR7: CT-006 | AS7: D+0 | AT7: 0 | AU7: Autorizado | AW7: Financeiro | AX7: 45688 | AY7: Ativa | AZ7: APL-006-202501 | BA7: =ROUND(T7-(O7+P7-Q7-R7+S7-IF(AK7="S",U7+V7,0)),2) -> 0 | BB7: =(O7+T7)/2 -> 1165350
A8: 45688 | B8: APL-007 | C8: Financiamento de Base | D8: CC-002 | E8: Banco Beta | F8: Tesouro Selic | G8: Tesouro Selic Banco Beta | H8: CDI | I8: 1.0022 | K8: 45455 | L8: 46335 | M8: No vencimento | N8: Longo prazo | O8: 469289.69 | P8: 0 | Q8: 0 | R8: 0 | S8: 4468.06 | T8: 473757.75 | U8: 0 | V8: 0 | W8: 670.21 | X8: 0 | Y8: 473087.54 | Z8: 0.009521 | AA8: 1.0022 | AD8: 0.0095 | AG8: 0.003 | AH8: 22 | AI8: 647 | AJ8: Acima de 360 dias | AK8: N | AL8: 0.15 | AM8: N | AN8: N | AO8: AA | AP8: Banco Beta | AQ8: Custodiante Ficticio | AR8: CT-007 | AS8: No vencimento | AT8: 0 | AU8: Autorizado | AW8: Financeiro | AX8: 45688 | AY8: Ativa | AZ8: APL-007-202501 | BA8: =ROUND(T8-(O8+P8-Q8-R8+S8-IF(AK8="S",U8+V8,0)),2) -> 0 | BB8: =(O8+T8)/2 -> 471523.72
A9: 45688 | B9: APL-008 | C9: Recursos de Terceiros | D9: CC-009 | E9: Banco Beta | F9: Fundo DI | G9: Fundo DI Banco Beta | H9: CDI | I9: 0.951 | K9: 45517 | M9: Diaria | N9: Curto prazo | O9: 844492.7 | P9: 200638.22 | Q9: 0 | R9: 0 | S9: 8535.9 | T9: 1052386.4 | U9: 1280.38 | V9: 0 | W9: 0 | X9: 0 | Y9: 1052386.4 | Z9: 0.008167 | AA9: 0.8597 | AD9: 0.0095 | AG9: 0.003 | AH9: 22 | AJ9: Liquidez diaria | AK9: S | AL9: 0.15 | AM9: N | AN9: N | AO9: AA+ | AP9: Banco Beta | AQ9: Custodiante Ficticio | AR9: CT-008 | AS9: D+0 | AT9: 0 | AU9: Autorizado | AW9: Financeiro | AX9: 45688 | AY9: Ativa | AZ9: APL-008-202501 | BA9: =ROUND(T9-(O9+P9-Q9-R9+S9-IF(AK9="S",U9+V9,0)),2) -> 0 | BB9: =(O9+T9)/2 -> 948439.57
A10: 45688 | B10: APL-009 | C10: Recursos Proprios | D10: CC-004 | E10: Banco Beta | F10: CDB | G10: CDB Banco Beta | H10: CDI | I10: 1.0439 | K10: 45317 | L10: 46577 | M10: No vencimento | N10: Longo prazo | O10: 1439591.1 | P10: 0 | Q10: 0 | R10: 0 | S10: 14276.5 | T10: 1453867.6 | U10: 0 | V10: 0 | W10: 2141.47 | X10: 0 | Y10: 1451726.2 | Z10: 0.009917 | AA10: 1.0439 | AD10: 0.0095 | AG10: 0.003 | AH10: 22 | AI10: 889 | AJ10: Acima de 360 dias | AK10: N | AL10: 0.15 | AM10: N | AN10: S | AO10: AA | AP10: Banco Beta | AQ10: Custodiante Ficticio | AR10: CT-009 | AS10: No vencimento | AT10: 0 | AU10: Autorizado | AW10: Financeiro | AX10: 45688 | AY10: Ativa | AZ10: APL-009-202501 | BA10: =ROUND(T10-(O10+P10-Q10-R10+S10-IF(AK10="S",U10+V10,0)),2) -> 0 | BB10: =(O10+T10)/2 -> 1446729.4
A11: 45688 | B11: APL-010 | C11: Recursos Proprios | D11: CC-005 | E11: Banco Beta | F11: Tesouro Selic | G11: Tesouro Selic Banco Beta | H11: CDI | I11: 0.9928 | K11: 45612 | L11: 47072 | M11: No vencimento | N11: Longo prazo | O11: 1875223 | P11: 0 | Q11: 0 | R11: 0 | S11: 17686.35 | T11: 1892909.4 | U11: 0 | V11: 0 | W11: 2652.95 | X11: 0 | Y11: 1890256.4 | Z11: 0.009432 | AA11: 0.9928 | AD11: 0.0095 | AG11: 0.003 | AH11: 22 | AI11: 1384 | AJ11: Acima de 360 dias | AK11: N | AL11: 0.15 | AM11: N | AN11: N | AO11: AAA | AP11: Banco Beta | AQ11: Custodiante Ficticio | AR11: CT-010 | AS11: No vencimento | AT11: 0 | AU11: Autorizado | AW11: Financeiro | AX11: 45688 | AY11: Ativa | AZ11: APL-010-202501 | BA11: =ROUND(T11-(O11+P11-Q11-R11+S11-IF(AK11="S",U11+V11,0)),2) -> 0 | BB11: =(O11+T11)/2 -> 1884066.2
A12: 45688 | B12: APL-011 | C12: Recursos de Terceiros | D12: CC-006 | E12: Banco Epsilon | F12: Fundo Aplic. Automatica | G12: Fundo Aplic. Automatica Banco Epsilon | H12: CDI | I12: 0.2329 | K12: 45492 | M12: Diaria | N12: Curto prazo | O12: 2493967.1 | P12: 0 | Q12: 0 | R12: 0 | S12: 5518.03 | T12: 2498657.5 | U12: 827.7 | V12: 0 | W12: 0 | X12: 0 | Y12: 2498657.5 | Z12: 0.002213 | AA12: 0.2329 | AD12: 0.0095 | AG12: 0.003 | AH12: 22 | AJ12: Liquidez diaria | AK12: S | AL12: 0.15 | AM12: N | AN12: N | AO12: AA+ | AP12: Banco Epsilon | AQ12: Custodiante Ficticio | AR12: CT-011 | AS12: D+0 | AT12: 0 | AU12: Autorizado | AW12: Financeiro | AX12: 45688 | AY12: Ativa | AZ12: APL-011-202501 | BA12: =ROUND(T12-(O12+P12-Q12-R12+S12-IF(AK12="S",U12+V12,0)),2) -> 0 | BB12: =(O12+T12)/2 -> 2496312.3
A13: 45688 | B13: APL-012 | C13: Recursos Proprios | D13: CC-003 | E13: Banco Alfa | F13: Compromissada | G13: Compromissada Banco Alfa | H13: CDI | I13: 0.8627 | K13: 45319 | M13: Diaria | N13: Curto prazo | O13: 1990594.4 | P13: 0 | Q13: 0 | R13: 0 | S13: 16314.22 | T13: 2006908.7 | U13: 0 | V13: 0 | W13: 2447.13 | X13: 0 | Y13: 2004461.5 | Z13: 0.008196 | AA13: 0.8627 | AD13: 0.0095 | AG13: 0.003 | AH13: 22 | AJ13: Liquidez diaria | AK13: N | AL13: 0.15 | AM13: N | AN13: N | AO13: AAA | AP13: Banco Alfa | AQ13: Custodiante Ficticio | AR13: CT-012 | AS13: D+0 | AT13: 0 | AU13: Autorizado | AW13: Financeiro | AX13: 45688 | AY13: Ativa | AZ13: APL-012-202501 | BA13: =ROUND(T13-(O13+P13-Q13-R13+S13-IF(AK13="S",U13+V13,0)),2) -> 0 | BB13: =(O13+T13)/2 -> 1998751.5
A14: 45688 | B14: APL-013 | C14: Financiamento de Base | D14: CC-005 | E14: Banco Epsilon | F14: Tesouro IPCA+ | G14: Tesouro IPCA+ Banco Epsilon | H14: IPCA | J14: 0.0055 | K14: 45335 | L14: 47041 | M14: No vencimento | N14: Longo prazo | O14: 2158910.3 | P14: 0 | Q14: 0 | R14: 43178.21 | S14: 18350.74 | T14: 2134082.8 | U14: 0 | V14: 0 | W14: 2752.61 | X14: 0 | Y14: 2131330.2 | Z14: 0.0085 | AA14: 0.8947 | AD14: 0.0095 | AG14: 0.003 | AH14: 22 | AI14: 1353 | AJ14: Acima de 360 dias | AK14: N | AL14: 0.15 | AM14: N | AN14: N | AO14: AAA | AP14: Banco Epsilon | AQ14: Custodiante Ficticio | AR14: CT-013 | AS14: No vencimento | AT14: 0 | AU14: Autorizado | AW14: Financeiro | AX14: 45688 | AY14: Ativa | AZ14: APL-013-202501 | BA14: =ROUND(T14-(O14+P14-Q14-R14+S14-IF(AK14="S",U14+V14,0)),2) -> 0 | BB14: =(O14+T14)/2 -> 2146496.5
A15: 45688 | B15: APL-014 | C15: Recursos Proprios | D15: CC-005 | E15: Banco Alfa | F15: CDB | G15: CDB Banco Alfa | H15: CDI | I15: 1.0104 | K15: 45614 | L15: 46702 | M15: No vencimento | N15: Longo prazo | O15: 1161623.1 | P15: 71814.75 | Q15: 0 | R15: 0 | S15: 11494.86 | T15: 1244932.7 | U15: 0 | V15: 0 | W15: 1724.23 | X15: 0 | Y15: 1243208.5 | Z15: 0.009319 | AA15: 0.981 | AD15: 0.0095 | AG15: 0.003 | AH15: 22 | AI15: 1014 | AJ15: Acima de 360 dias | AK15: N | AL15: 0.15 | AM15: N | AN15: S | AO15: AA+ | AP15: Banco Alfa | AQ15: Custodiante Ficticio | AR15: CT-014 | AS15: No vencimento | AT15: 0 | AU15: Autorizado | AW15: Financeiro | AX15: 45688 | AY15: Ativa | AZ15: APL-014-202501 | BA15: =ROUND(T15-(O15+P15-Q15-R15+S15-IF(AK15="S",U15+V15,0)),2) -> 0 | BB15: =(O15+T15)/2 -> 1203277.9
A16: 45688 | B16: APL-015 | C16: Recursos Proprios | D16: CC-005 | E16: Banco Epsilon | F16: Fundo Aplic. Automatica | G16: Fundo Aplic. Automatica Banco Epsilon | H16: CDI | I16: 0.3263 | K16: 45368 | M16: Diaria | N16: Curto prazo | O16: 1293774.1 | P16: 0 | Q16: 0 | R16: 0 | S16: 4010.51 | T16: 1297183 | U16: 601.58 | V16: 0 | W16: 0 | X16: 0 | Y16: 1297183 | Z16: 0.0031 | AA16: 0.3263 | AD16: 0.0095 | AG16: 0.003 | AH16: 22 | AJ16: Liquidez diaria | AK16: S | AL16: 0.15 | AM16: N | AN16: N | AO16: AA+ | AP16: Banco Epsilon | AQ16: Custodiante Ficticio | AR16: CT-015 | AS16: D+0 | AT16: 0 | AU16: Autorizado | AW16: Financeiro | AX16: 45688 | AY16: Ativa | AZ16: APL-015-202501 | BA16: =ROUND(T16-(O16+P16-Q16-R16+S16-IF(AK16="S",U16+V16,0)),2) -> 0 | BB16: =(O16+T16)/2 -> 1295478.5
A17: 45688 | B17: APL-016 | C17: Recursos Proprios | D17: CC-009 | E17: Banco Beta | F17: Fundo DI | G17: Fundo DI Banco Beta | H17: CDI | I17: 0.9877 | K17: 45468 | M17: Diaria | N17: Curto prazo | O17: 2309963.5 | P17: 0 | Q17: 0 | R17: 0 | S17: 21674.73 | T17: 2328387 | U17: 3251.21 | V17: 0 | W17: 0 | X17: 0 | Y17: 2328387 | Z17: 0.009383 | AA17: 0.9877 | AD17: 0.0095 | AG17: 0.003 | AH17: 22 | AJ17: Liquidez diaria | AK17: S | AL17: 0.15 | AM17: N | AN17: N | AO17: AA | AP17: Banco Beta | AQ17: Custodiante Ficticio | AR17: CT-016 | AS17: D+0 | AT17: 0 | AU17: Autorizado | AW17: Financeiro | AX17: 45688 | AY17: Ativa | AZ17: APL-016-202501 | BA17: =ROUND(T17-(O17+P17-Q17-R17+S17-IF(AK17="S",U17+V17,0)),2) -> 0 | BB17: =(O17+T17)/2 -> 2319175.3
A18: 45688 | B18: APL-017 | C18: Recursos de Terceiros | D18: CC-004 | E18: Banco Epsilon | F18: CDB | G18: CDB Banco Epsilon | H18: CDI | I18: 0.9841 | K18: 45459 | L18: 45700 | M18: No vencimento | N18: Curto prazo | O18: 2201123.5 | P18: 0 | Q18: 0 | R18: 0 | S18: 20578.19 | T18: 2221701.7 | U18: 0 | V18: 0 | W18: 3086.73 | X18: 0 | Y18: 2218615 | Z18: 0.009349 | AA18: 0.9841 | AD18: 0.0095 | AG18: 0.003 | AH18: 22 | AI18: 12 | AJ18: Ate 90 dias | AK18: N | AL18: 0.15 | AM18: N | AN18: S | AO18: AA | AP18: Banco Epsilon | AQ18: Custodiante Ficticio | AR18: CT-017 | AS18: No vencimento | AT18: 0 | AU18: Autorizado | AW18: Financeiro | AX18: 45688 | AY18: Ativa | AZ18: APL-017-202501 | BA18: =ROUND(T18-(O18+P18-Q18-R18+S18-IF(AK18="S",U18+V18,0)),2) -> 0 | BB18: =(O18+T18)/2 -> 2211412.6
A19: 45688 | B19: APL-018 | C19: Recursos Proprios | D19: CC-003 | E19: Banco Alfa | F19: LCA | G19: LCA Banco Alfa | H19: CDI | I19: 0.9262 | K19: 45642 | L19: 45925 | M19: No vencimento | N19: Curto prazo | O19: 2369779.3 | P19: 0 | Q19: 0 | R19: 0 | S19: 20851.45 | T19: 2390630.7 | U19: 0 | V19: 0 | W19: 0 | X19: 0 | Y19: 2390630.7 | Z19: 0.008799 | AA19: 0.9262 | AD19: 0.0095 | AG19: 0.003 | AH19: 22 | AI19: 237 | AJ19: 91 a 360 dias | AK19: N | AL19: 0 | AM19: S | AN19: S | AO19: AA | AP19: Banco Alfa | AQ19: Custodiante Ficticio | AR19: CT-018 | AS19: No vencimento | AT19: 0 | AU19: Autorizado | AW19: Financeiro | AX19: 45688 | AY19: Ativa | AZ19: APL-018-202501 | BA19: =ROUND(T19-(O19+P19-Q19-R19+S19-IF(AK19="S",U19+V19,0)),2) -> 0 | BB19: =(O19+T19)/2 -> 2380205
A20: 45688 | B20: APL-019 | C20: Financiamento de Base | D20: CC-004 | E20: Banco Gama | F20: LCI | G20: LCI Banco Gama | H20: CDI | I20: 0.9199 | K20: 45563 | L20: 47306 | M20: No vencimento | N20: Longo prazo | O20: 1027531.1 | P20: 0 | Q20: 0 | R20: 0 | S20: 8979.65 | T20: 1036510.8 | U20: 0 | V20: 0 | W20: 0 | X20: 0 | Y20: 1036510.8 | Z20: 0.008739 | AA20: 0.9199 | AD20: 0.0095 | AG20: 0.003 | AH20: 22 | AI20: 1618 | AJ20: Acima de 360 dias | AK20: N | AL20: 0 | AM20: S | AN20: S | AO20: AAA | AP20: Banco Gama | AQ20: Custodiante Ficticio | AR20: CT-019 | AS20: No vencimento | AT20: 0 | AU20: Autorizado | AW20: Financeiro | AX20: 45688 | AY20: Ativa | AZ20: APL-019-202501 | BA20: =ROUND(T20-(O20+P20-Q20-R20+S20-IF(AK20="S",U20+V20,0)),2) -> 0 | BB20: =(O20+T20)/2 -> 1032021
A21: 45688 | B21: APL-020 | C21: Recursos Proprios | D21: CC-006 | E21: Cooperativa Delta | F21: Tesouro Selic | G21: Tesouro Selic Cooperativa Delta | H21: CDI | I21: 0.9904 | K21: 45550 | L21: 45755 | M21: No vencimento | N21: Curto prazo | O21: 1407107.7 | P21: 0 | Q21: 0 | R21: 0 | S21: 13239.2 | T21: 1420346.9 | U21: 0 | V21: 0 | W21: 1985.88 | X21: 0 | Y21: 1418361.1 | Z21: 0.009409 | AA21: 0.9904 | AD21: 0.0095 | AG21: 0.003 | AH21: 22 | AI21: 67 | AJ21: Ate 90 dias | AK21: N | AL21: 0.15 | AM21: N | AN21: N | AO21: AA | AP21: Cooperativa Delta | AQ21: Custodiante Ficticio | AR21: CT-020 | AS21: No vencimento | AT21: 0 | AU21: Autorizado | AW21: Financeiro | AX21: 45688 | AY21: Ativa | AZ21: APL-020-202501 | BA21: =ROUND(T21-(O21+P21-Q21-R21+S21-IF(AK21="S",U21+V21,0)),2) -> 0 | BB21: =(O21+T21)/2 -> 1413727.3
A22: 45688 | B22: APL-021 | C22: Financiamento de Base | D22: CC-001 | E22: Banco Alfa | F22: Fundo DI | G22: Fundo DI Banco Alfa | H22: CDI | I22: 0.9514 | K22: 45345 | M22: Diaria | N22: Curto prazo | O22: 2268279 | P22: 0 | Q22: 0 | R22: 0 | S22: 20501.39 | T22: 2285705.2 | U22: 3075.21 | V22: 0 | W22: 0 | X22: 0 | Y22: 2285705.2 | Z22: 0.009038 | AA22: 0.9514 | AD22: 0.0095 | AG22: 0.003 | AH22: 22 | AJ22: Liquidez diaria | AK22: S | AL22: 0.15 | AM22: N | AN22: N | AO22: AA | AP22: Banco Alfa | AQ22: Custodiante Ficticio | AR22: CT-021 | AS22: D+0 | AT22: 0 | AU22: Autorizado | AW22: Financeiro | AX22: 45688 | AY22: Ativa | AZ22: APL-021-202501 | BA22: =ROUND(T22-(O22+P22-Q22-R22+S22-IF(AK22="S",U22+V22,0)),2) -> 0 | BB22: =(O22+T22)/2 -> 2276992.1
A23: 45688 | B23: APL-022 | C23: Recursos Proprios | D23: CC-009 | E23: Banco Alfa | F23: Tesouro Selic | G23: Tesouro Selic Banco Alfa | H23: CDI | I23: 0.9926 | K23: 45543 | L23: 46707 | M23: No vencimento | N23: Longo prazo | O23: 2342009.9 | P23: 0 | Q23: 0 | R23: 0 | S23: 22084.45 | T23: 2364094.3 | U23: 0 | V23: 0 | W23: 3312.67 | X23: 0 | Y23: 2360781.7 | Z23: 0.00943 | AA23: 0.9926 | AD23: 0.0095 | AG23: 0.003 | AH23: 22 | AI23: 1019 | AJ23: Acima de 360 dias | AK23: N | AL23: 0.15 | AM23: N | AN23: N | AO23: AA | AP23: Banco Alfa | AQ23: Custodiante Ficticio | AR23: CT-022 | AS23: No vencimento | AT23: 0 | AU23: Autorizado | AW23: Financeiro | AX23: 45688 | AY23: Ativa | AZ23: APL-022-202501 | BA23: =ROUND(T23-(O23+P23-Q23-R23+S23-IF(AK23="S",U23+V23,0)),2) -> 0 | BB23: =(O23+T23)/2 -> 2353052.1
A24: 45688 | B24: APL-023 | C24: Recursos de Terceiros | D24: CC-004 | E24: Banco Beta | F24: Compromissada | G24: Compromissada Banco Beta | H24: CDI | I24: 0.8094 | K24: 45530 | M24: Diaria | N24: Curto prazo | O24: 1664507.7 | P24: 0 | Q24: 0 | R24: 0 | S24: 12798.9 | T24: 1677306.6 | U24: 0 | V24: 0 | W24: 1919.83 | X24: 0 | Y24: 1675386.8 | Z24: 0.007689 | AA24: 0.8094 | AD24: 0.0095 | AG24: 0.003 | AH24: 22 | AJ24: Liquidez diaria | AK24: N | AL24: 0.15 | AM24: N | AN24: N | AO24: AA+ | AP24: Banco Beta | AQ24: Custodiante Ficticio | AR24: CT-023 | AS24: D+0 | AT24: 0 | AU24: Autorizado | AW24: Financeiro | AX24: 45688 | AY24: Ativa | AZ24: APL-023-202501 | BA24: =ROUND(T24-(O24+P24-Q24-R24+S24-IF(AK24="S",U24+V24,0)),2) -> 0 | BB24: =(O24+T24)/2 -> 1670907.2
A25: 45688 | B25: APL-024 | C25: Financiamento de Base | D25: CC-002 | E25: Cooperativa Delta | F25: Tesouro Selic | G25: Tesouro Selic Cooperativa Delta | H25: CDI | I25: 0.9912 | K25: 45488 | L25: 45982 | M25: No vencimento | N25: Curto prazo | O25: 1834123.3 | P25: 0 | Q25: 0 | R25: 0 | S25: 17270.84 | T25: 1851394.1 | U25: 0 | V25: 0 | W25: 2590.63 | X25: 0 | Y25: 1848803.5 | Z25: 0.009416 | AA25: 0.9912 | AD25: 0.0095 | AG25: 0.003 | AH25: 22 | AI25: 294 | AJ25: 91 a 360 dias | AK25: N | AL25: 0.15 | AM25: N | AN25: N | AO25: AAA | AP25: Cooperativa Delta | AQ25: Custodiante Ficticio | AR25: CT-024 | AS25: No vencimento | AT25: 0 | AU25: Autorizado | AW25: Financeiro | AX25: 45688 | AY25: Ativa | AZ25: APL-024-202501 | BA25: =ROUND(T25-(O25+P25-Q25-R25+S25-IF(AK25="S",U25+V25,0)),2) -> 0 | BB25: =(O25+T25)/2 -> 1842758.7
A26: 45688 | B26: APL-025 | C26: Recursos de Terceiros | D26: CC-003 | E26: Banco Beta | F26: LCA | G26: LCA Banco Beta | H26: CDI | I26: 0.8995 | K26: 45389 | L26: 47335 | M26: No vencimento | N26: Longo prazo | O26: 662025.8 | P26: 132836.97 | Q26: 0 | R26: 0 | S26: 6224.74 | T26: 801087.51 | U26: 0 | V26: 0 | W26: 0 | X26: 0 | Y26: 801087.51 | Z26: 0.007831 | AA26: 0.8243 | AD26: 0.0095 | AG26: 0.003 | AH26: 22 | AI26: 1647 | AJ26: Acima de 360 dias | AK26: N | AL26: 0 | AM26: S | AN26: S | AO26: AAA | AP26: Banco Beta | AQ26: Custodiante Ficticio | AR26: CT-025 | AS26: No vencimento | AT26: 0 | AU26: Autorizado | AW26: Financeiro | AX26: 45688 | AY26: Ativa | AZ26: APL-025-202501 | BA26: =ROUND(T26-(O26+P26-Q26-R26+S26-IF(AK26="S",U26+V26,0)),2) -> 0 | BB26: =(O26+T26)/2 -> 731556.66
A27: 45688 | B27: APL-026 | C27: Recursos Proprios | D27: CC-002 | E27: Cooperativa Delta | F27: LCA | G27: LCA Cooperativa Delta | H27: CDI | I27: 0.9448 | K27: 45539 | L27: 45979 | M27: No vencimento | N27: Curto prazo | O27: 2129304.5 | P27: 0 | Q27: 392121.2 | R27: 0 | S27: 17352.02 | T27: 1754535.4 | U27: 0 | V27: 0 | W27: 0 | X27: 0 | Y27: 1754535.4 | Z27: 0.008149 | AA27: 0.8578 | AD27: 0.0095 | AG27: 0.003 | AH27: 22 | AI27: 291 | AJ27: 91 a 360 dias | AK27: N | AL27: 0 | AM27: S | AN27: S | AO27: AAA | AP27: Cooperativa Delta | AQ27: Custodiante Ficticio | AR27: CT-026 | AS27: No vencimento | AT27: 0 | AU27: Autorizado | AW27: Financeiro | AX27: 45688 | AY27: Ativa | AZ27: APL-026-202501 | BA27: =ROUND(T27-(O27+P27-Q27-R27+S27-IF(AK27="S",U27+V27,0)),2) -> 0 | BB27: =(O27+T27)/2 -> 1941920
A28: 45688 | B28: APL-027 | C28: Recursos Proprios | D28: CC-007 | E28: Cooperativa Delta | F28: LCI | G28: LCI Cooperativa Delta | H28: CDI | I28: 0.8702 | K28: 45520 | L28: 46205 | M28: No vencimento | N28: Longo prazo | O28: 1006533.3 | P28: 0 | Q28: 0 | R28: 0 | S28: 8320.91 | T28: 1014854.2 | U28: 0 | V28: 0 | W28: 0 | X28: 0 | Y28: 1014854.2 | Z28: 0.008267 | AA28: 0.8702 | AD28: 0.0095 | AG28: 0.003 | AH28: 22 | AI28: 517 | AJ28: Acima de 360 dias | AK28: N | AL28: 0 | AM28: S | AN28: S | AO28: AA+ | AP28: Cooperativa Delta | AQ28: Custodiante Ficticio | AR28: CT-027 | AS28: No vencimento | AT28: 0 | AU28: Autorizado | AW28: Financeiro | AX28: 45688 | AY28: Ativa | AZ28: APL-027-202501 | BA28: =ROUND(T28-(O28+P28-Q28-R28+S28-IF(AK28="S",U28+V28,0)),2) -> 0 | BB28: =(O28+T28)/2 -> 1010693.8
A29: 45688 | B29: APL-028 | C29: Financiamento de Base | D29: CC-009 | E29: Banco Gama | F29: Compromissada | G29: Compromissada Banco Gama | H29: CDI | I29: 0.8662 | K29: 45496 | M29: Diaria | N29: Curto prazo | O29: 1242345 | P29: 0 | Q29: 378569.87 | R29: 0 | S29: 8665.53 | T29: 872440.62 | U29: 0 | V29: 0 | W29: 1299.83 | X29: 0 | Y29: 871140.79 | Z29: 0.006975 | AA29: 0.7342 | AD29: 0.0095 | AG29: 0.003 | AH29: 22 | AJ29: Liquidez diaria | AK29: N | AL29: 0.15 | AM29: N | AN29: N | AO29: AA | AP29: Banco Gama | AQ29: Custodiante Ficticio | AR29: CT-028 | AS29: D+0 | AT29: 0 | AU29: Autorizado | AW29: Financeiro | AX29: 45688 | AY29: Ativa | AZ29: APL-028-202501 | BA29: =ROUND(T29-(O29+P29-Q29-R29+S29-IF(AK29="S",U29+V29,0)),2) -> 0 | BB29: =(O29+T29)/2 -> 1057392.8
A30: 45716 | B30: APL-001 | C30: Financiamento de Base | D30: CC-002 | E30: Banco Alfa | F30: LCA | G30: LCA Banco Alfa | H30: CDI | I30: 0.9274 | K30: 45635 | L30: 46117 | M30: No vencimento | N30: Longo prazo | O30: 2255538.4 | P30: 0 | Q30: 0 | R30: 0 | S30: 18407.72 | T30: 2273946.1 | U30: 0 | V30: 0 | W30: 0 | X30: 0 | Y30: 2273946.1 | Z30: 0.008161 | AA30: 0.9274 | AD30: 0.0088 | AG30: 0.0045 | AH30: 18 | AI30: 401 | AJ30: Acima de 360 dias | AK30: N | AL30: 0 | AM30: S | AN30: S | AO30: AA+ | AP30: Banco Alfa | AQ30: Custodiante Ficticio | AR30: CT-001 | AS30: No vencimento | AT30: 0 | AU30: Autorizado | AW30: Financeiro | AX30: 45716 | AY30: Ativa | AZ30: APL-001-202502 | BA30: =ROUND(T30-(O30+P30-Q30-R30+S30-IF(AK30="S",U30+V30,0)),2) -> 0 | BB30: =(O30+T30)/2 -> 2264742.2
A31: 45716 | B31: APL-002 | C31: Recursos Proprios | D31: CC-009 | E31: Banco Epsilon | F31: LCA | G31: LCA Banco Epsilon | H31: CDI | I31: 0.9221 | K31: 45475 | L31: 45695 | M31: No vencimento | N31: Curto prazo | O31: 1437533.8 | P31: 0 | Q31: 59703.75 | R31: 0 | S31: 11422.61 | T31: 1389252.6 | U31: 0 | V31: 0 | W31: 0 | X31: 0 | Y31: 1389252.6 | Z31: 0.007946 | AA31: 0.903 | AD31: 0.0088 | AG31: 0.0045 | AH31: 18 | AI31: -21 | AJ31: Ate 90 dias | AK31: N | AL31: 0 | AM31: S | AN31: S | AO31: AA+ | AP31: Banco Epsilon | AQ31: Custodiante Ficticio | AR31: CT-002 | AS31: No vencimento | AT31: 0 | AU31: Autorizado | AW31: Financeiro | AX31: 45716 | AY31: Ativa | AZ31: APL-002-202502 | BA31: =ROUND(T31-(O31+P31-Q31-R31+S31-IF(AK31="S",U31+V31,0)),2) -> 0 | BB31: =(O31+T31)/2 -> 1413393.2
A32: 45716 | B32: APL-003 | C32: Recursos Proprios | D32: CC-007 | E32: Banco Beta | F32: Tesouro IPCA+ | G32: Tesouro IPCA+ Banco Beta | H32: IPCA | J32: 0.0048 | K32: 45523 | L32: 46412 | M32: No vencimento | N32: Longo prazo | O32: 228955.77 | P32: 0 | Q32: 0 | R32: 0 | S32: 2129.29 | T32: 231085.06 | U32: 0 | V32: 0 | W32: 319.39 | X32: 0 | Y32: 230765.67 | Z32: 0.0093 | AA32: 1.0568 | AD32: 0.0088 | AG32: 0.0045 | AH32: 18 | AI32: 696 | AJ32: Acima de 360 dias | AK32: N | AL32: 0.15 | AM32: N | AN32: N | AO32: AAA | AP32: Banco Beta | AQ32: Custodiante Ficticio | AR32: CT-003 | AS32: No vencimento | AT32: 0 | AU32: Autorizado | AW32: Financeiro | AX32: 45716 | AY32: Ativa | AZ32: APL-003-202502 | BA32: =ROUND(T32-(O32+P32-Q32-R32+S32-IF(AK32="S",U32+V32,0)),2) -> 0 | BB32: =(O32+T32)/2 -> 230020.41
A33: 45716 | B33: APL-004 | C33: Recursos de Terceiros | D33: CC-005 | E33: Banco Alfa | F33: Tesouro Selic | G33: Tesouro Selic Banco Alfa | H33: CDI | I33: 1.0061 | K33: 45335 | L33: 45836 | M33: No vencimento | N33: Curto prazo | O33: 1855408.9 | P33: 0 | Q33: 0 | R33: 0 | S33: 16427.2 | T33: 1871836.1 | U33: 0 | V33: 0 | W33: 2464.08 | X33: 0 | Y33: 1869372 | Z33: 0.008854 | AA33: 1.0061 | AD33: 0.0088 | AG33: 0.0045 | AH33: 18 | AI33: 120 | AJ33: 91 a 360 dias | AK33: N | AL33: 0.15 | AM33: N | AN33: N | AO33: AAA | AP33: Banco Alfa | AQ33: Custodiante Ficticio | AR33: CT-004 | AS33: No vencimento | AT33: 0 | AU33: Autorizado | AW33: Financeiro | AX33: 45716 | AY33: Ativa | AZ33: APL-004-202502 | BA33: =ROUND(T33-(O33+P33-Q33-R33+S33-IF(AK33="S",U33+V33,0)),2) -> 0 | BB33: =(O33+T33)/2 -> 1863622.5
A34: 45716 | B34: APL-005 | C34: Recursos de Terceiros | D34: CC-004 | E34: Cooperativa Delta | F34: LCA | G34: LCA Cooperativa Delta | H34: CDI | I34: 0.9293 | K34: 45340 | L34: 46711 | M34: No vencimento | N34: Longo prazo | O34: 127036.44 | P34: 0 | Q34: 0 | R34: 0 | S34: 1038.88 | T34: 128075.32 | U34: 0 | V34: 0 | W34: 0 | X34: 0 | Y34: 128075.32 | Z34: 0.008178 | AA34: 0.9293 | AD34: 0.0088 | AG34: 0.0045 | AH34: 18 | AI34: 995 | AJ34: Acima de 360 dias | AK34: N | AL34: 0 | AM34: S | AN34: S | AO34: AA | AP34: Cooperativa Delta | AQ34: Custodiante Ficticio | AR34: CT-005 | AS34: No vencimento | AT34: 0 | AU34: Autorizado | AW34: Financeiro | AX34: 45716 | AY34: Ativa | AZ34: APL-005-202502 | BA34: =ROUND(T34-(O34+P34-Q34-R34+S34-IF(AK34="S",U34+V34,0)),2) -> 0 | BB34: =(O34+T34)/2 -> 127555.88
A35: 45716 | B35: APL-006 | C35: Recursos Proprios | D35: CC-002 | E35: Banco Gama | F35: Fundo DI | G35: Fundo DI Banco Gama | H35: CDI | I35: 0.959 | K35: 45350 | M35: Diaria | N35: Curto prazo | O35: 1169844.8 | P35: 0 | Q35: 0 | R35: 0 | S35: 9872.55 | T35: 1178236.5 | U35: 1480.88 | V35: 0 | W35: 0 | X35: 0 | Y35: 1178236.5 | Z35: 0.008439 | AA35: 0.959 | AD35: 0.0088 | AG35: 0.0045 | AH35: 18 | AJ35: Liquidez diaria | AK35: S | AL35: 0.15 | AM35: N | AN35: N | AO35: AA | AP35: Banco Gama | AQ35: Custodiante Ficticio | AR35: CT-006 | AS35: D+0 | AT35: 0 | AU35: Autorizado | AW35: Financeiro | AX35: 45716 | AY35: Ativa | AZ35: APL-006-202502 | BA35: =ROUND(T35-(O35+P35-Q35-R35+S35-IF(AK35="S",U35+V35,0)),2) -> 0 | BB35: =(O35+T35)/2 -> 1174040.6
A36: 45716 | B36: APL-007 | C36: Financiamento de Base | D36: CC-002 | E36: Banco Beta | F36: Tesouro Selic | G36: Tesouro Selic Banco Beta | H36: CDI | I36: 1.0022 | K36: 45455 | L36: 46335 | M36: No vencimento | N36: Longo prazo | O36: 473757.75 | P36: 0 | Q36: 0 | R36: 0 | S36: 4178.24 | T36: 477935.99 | U36: 0 | V36: 0 | W36: 626.74 | X36: 0 | Y36: 477309.25 | Z36: 0.008819 | AA36: 1.0022 | AD36: 0.0088 | AG36: 0.0045 | AH36: 18 | AI36: 619 | AJ36: Acima de 360 dias | AK36: N | AL36: 0.15 | AM36: N | AN36: N | AO36: AAA | AP36: Banco Beta | AQ36: Custodiante Ficticio | AR36: CT-007 | AS36: No vencimento | AT36: 0 | AU36: Autorizado | AW36: Financeiro | AX36: 45716 | AY36: Ativa | AZ36: APL-007-202502 | BA36: =ROUND(T36-(O36+P36-Q36-R36+S36-IF(AK36="S",U36+V36,0)),2) -> 0 | BB36: =(O36+T36)/2 -> 475846.87
A37: 45716 | B37: APL-008 | C37: Recursos de Terceiros | D37: CC-009 | E37: Banco Beta | F37: Fundo DI | G37: Fundo DI Banco Beta | H37: CDI | I37: 0.951 | K37: 45517 | M37: Diaria | N37: Curto prazo | O37: 1052386.4 | P37: 0 | Q37: 0 | R37: 0 | S37: 8807.21 | T37: 1059872.6 | U37: 1321.08 | V37: 0 | W37: 0 | X37: 0 | Y37: 1059872.6 | Z37: 0.008369 | AA37: 0.951 | AD37: 0.0088 | AG37: 0.0045 | AH37: 18 | AJ37: Liquidez diaria | AK37: S | AL37: 0.15 | AM37: N | AN37: N | AO37: AAA | AP37: Banco Beta | AQ37: Custodiante Ficticio | AR37: CT-008 | AS37: D+0 | AT37: 0 | AU37: Autorizado | AW37: Financeiro | AX37: 45716 | AY37: Ativa | AZ37: APL-008-202502 | BA37: =ROUND(T37-(O37+P37-Q37-R37+S37-IF(AK37="S",U37+V37,0)),2) -> 0 | BB37: =(O37+T37)/2 -> 1056129.5
A38: 45716 | B38: APL-009 | C38: Recursos Proprios | D38: CC-004 | E38: Banco Beta | F38: CDB | G38: CDB Banco Beta | H38: CDI | I38: 1.0439 | K38: 45317 | L38: 46577 | M38: No vencimento | N38: Longo prazo | O38: 1453867.6 | P38: 0 | Q38: 297260.14 | R38: 0 | S38: 11990.33 | T38: 1168597.8 | U38: 0 | V38: 0 | W38: 1798.55 | X38: 0 | Y38: 1166799.3 | Z38: 0.008247 | AA38: 0.9372 | AD38: 0.0088 | AG38: 0.0045 | AH38: 18 | AI38: 861 | AJ38: Acima de 360 dias | AK38: N | AL38: 0.15 | AM38: N | AN38: S | AO38: AA+ | AP38: Banco Beta | AQ38: Custodiante Ficticio | AR38: CT-009 | AS38: No vencimento | AT38: 0 | AU38: Autorizado | AW38: Financeiro | AX38: 45716 | AY38: Ativa | AZ38: APL-009-202502 | BA38: =ROUND(T38-(O38+P38-Q38-R38+S38-IF(AK38="S",U38+V38,0)),2) -> 0 | BB38: =(O38+T38)/2 -> 1311232.7
A39: 45716 | B39: APL-010 | C39: Recursos Proprios | D39: CC-005 | E39: Banco Beta | F39: Tesouro Selic | G39: Tesouro Selic Banco Beta | H39: CDI | I39: 0.9928 | K39: 45612 | L39: 47072 | M39: No vencimento | N39: Longo prazo | O39: 1892909.4 | P39: 0 | Q39: 0 | R39: 0 | S39: 16537.67 | T39: 1909447 | U39: 0 | V39: 0 | W39: 2480.65 | X39: 0 | Y39: 1906966.4 | Z39: 0.008737 | AA39: 0.9928 | AD39: 0.0088 | AG39: 0.0045 | AH39: 18 | AI39: 1356 | AJ39: Acima de 360 dias | AK39: N | AL39: 0.15 | AM39: N | AN39: N | AO39: AA | AP39: Banco Beta | AQ39: Custodiante Ficticio | AR39: CT-010 | AS39: No vencimento | AT39: 0 | AU39: Autorizado | AW39: Financeiro | AX39: 45716 | AY39: Ativa | AZ39: APL-010-202502 | BA39: =ROUND(T39-(O39+P39-Q39-R39+S39-IF(AK39="S",U39+V39,0)),2) -> 0 | BB39: =(O39+T39)/2 -> 1901178.2
A40: 45716 | B40: APL-011 | C40: Recursos de Terceiros | D40: CC-006 | E40: Banco Epsilon | F40: Fundo Aplic. Automatica | G40: Fundo Aplic. Automatica Banco Epsilon | H40: CDI | I40: 0.2329 | K40: 45492 | M40: Diaria | N40: Curto prazo | O40: 2498657.5 | P40: 0 | Q40: 0 | R40: 0 | S40: 5121.05 | T40: 2503010.4 | U40: 768.16 | V40: 0 | W40: 0 | X40: 0 | Y40: 2503010.4 | Z40: 0.00205 | AA40: 0.2329 | AD40: 0.0088 | AG40: 0.0045 | AH40: 18 | AJ40: Liquidez diaria | AK40: S | AL40: 0.15 | AM40: N | AN40: N | AO40: AA+ | AP40: Banco Epsilon | AQ40: Custodiante Ficticio | AR40: CT-011 | AS40: D+0 | AT40: 0 | AU40: Autorizado | AW40: Financeiro | AX40: 45716 | AY40: Ativa | AZ40: APL-011-202502 | BA40: =ROUND(T40-(O40+P40-Q40-R40+S40-IF(AK40="S",U40+V40,0)),2) -> 0 | BB40: =(O40+T40)/2 -> 2500833.9
A41: 45716 | B41: APL-012 | C41: Recursos Proprios | D41: CC-003 | E41: Banco Alfa | F41: Compromissada | G41: Compromissada Banco Alfa | H41: CDI | I41: 0.8627 | K41: 45319 | M41: Diaria | N41: Curto prazo | O41: 2006908.7 | P41: 0 | Q41: 0 | R41: 0 | S41: 15235.97 | T41: 2022144.6 | U41: 0 | V41: 0 | W41: 2285.4 | X41: 0 | Y41: 2019859.2 | Z41: 0.007592 | AA41: 0.8627 | AD41: 0.0088 | AG41: 0.0045 | AH41: 18 | AJ41: Liquidez diaria | AK41: N | AL41: 0.15 | AM41: N | AN41: N | AO41: AA+ | AP41: Banco Alfa | AQ41: Custodiante Ficticio | AR41: CT-012 | AS41: D+0 | AT41: 0 | AU41: Autorizado | AW41: Financeiro | AX41: 45716 | AY41: Ativa | AZ41: APL-012-202502 | BA41: =ROUND(T41-(O41+P41-Q41-R41+S41-IF(AK41="S",U41+V41,0)),2) -> 0 | BB41: =(O41+T41)/2 -> 2014526.6
A42: 45716 | B42: APL-013 | C42: Financiamento de Base | D42: CC-005 | E42: Banco Epsilon | F42: Tesouro IPCA+ | G42: Tesouro IPCA+ Banco Epsilon | H42: IPCA | J42: 0.0055 | K42: 45335 | L42: 47041 | M42: No vencimento | N42: Longo prazo | O42: 2134082.8 | P42: 0 | Q42: 0 | R42: 0 | S42: 21340.83 | T42: 2155423.6 | U42: 0 | V42: 0 | W42: 3201.12 | X42: 0 | Y42: 2152222.5 | Z42: 0.01 | AA42: 1.1364 | AD42: 0.0088 | AG42: 0.0045 | AH42: 18 | AI42: 1325 | AJ42: Acima de 360 dias | AK42: N | AL42: 0.15 | AM42: N | AN42: N | AO42: AAA | AP42: Banco Epsilon | AQ42: Custodiante Ficticio | AR42: CT-013 | AS42: No vencimento | AT42: 0 | AU42: Autorizado | AW42: Financeiro | AX42: 45716 | AY42: Ativa | AZ42: APL-013-202502 | BA42: =ROUND(T42-(O42+P42-Q42-R42+S42-IF(AK42="S",U42+V42,0)),2) -> 0 | BB42: =(O42+T42)/2 -> 2144753.2
A43: 45716 | B43: APL-014 | C43: Recursos Proprios | D43: CC-005 | E43: Banco Alfa | F43: CDB | G43: CDB Banco Alfa | H43: CDI | I43: 1.0104 | K43: 45614 | L43: 46702 | M43: No vencimento | N43: Longo prazo | O43: 1244932.7 | P43: 0 | Q43: 0 | R43: 0 | S43: 11069.34 | T43: 1256002 | U43: 0 | V43: 0 | W43: 1660.4 | X43: 0 | Y43: 1254341.6 | Z43: 0.008892 | AA43: 1.0104 | AD43: 0.0088 | AG43: 0.0045 | AH43: 18 | AI43: 986 | AJ43: Acima de 360 dias | AK43: N | AL43: 0.15 | AM43: N | AN43: S | AO43: AA+ | AP43: Banco Alfa | AQ43: Custodiante Ficticio | AR43: CT-014 | AS43: No vencimento | AT43: 0 | AU43: Autorizado | AW43: Financeiro | AX43: 45716 | AY43: Ativa | AZ43: APL-014-202502 | BA43: =ROUND(T43-(O43+P43-Q43-R43+S43-IF(AK43="S",U43+V43,0)),2) -> 0 | BB43: =(O43+T43)/2 -> 1250467.4
A44: 45716 | B44: APL-015 | C44: Recursos Proprios | D44: CC-005 | E44: Banco Epsilon | F44: Fundo Aplic. Automatica | G44: Fundo Aplic. Automatica Banco Epsilon | H44: CDI | I44: 0.3263 | K44: 45368 | M44: Diaria | N44: Curto prazo | O44: 1297183 | P44: 0 | Q44: 0 | R44: 0 | S44: 3724.78 | T44: 1300349.1 | U44: 558.72 | V44: 0 | W44: 0 | X44: 0 | Y44: 1300349.1 | Z44: 0.002871 | AA44: 0.3263 | AD44: 0.0088 | AG44: 0.0045 | AH44: 18 | AJ44: Liquidez diaria | AK44: S | AL44: 0.15 | AM44: N | AN44: N | AO44: AAA | AP44: Banco Epsilon | AQ44: Custodiante Ficticio | AR44: CT-015 | AS44: D+0 | AT44: 0 | AU44: Autorizado | AW44: Financeiro | AX44: 45716 | AY44: Ativa | AZ44: APL-015-202502 | BA44: =ROUND(T44-(O44+P44-Q44-R44+S44-IF(AK44="S",U44+V44,0)),2) -> 0 | BB44: =(O44+T44)/2 -> 1298766
A45: 45716 | B45: APL-016 | C45: Recursos Proprios | D45: CC-009 | E45: Banco Beta | F45: Fundo DI | G45: Fundo DI Banco Beta | H45: CDI | I45: 0.9877 | K45: 45468 | M45: Diaria | N45: Curto prazo | O45: 2328387 | P45: 0 | Q45: 0 | R45: 0 | S45: 20237.78 | T45: 2345589.1 | U45: 3035.67 | V45: 0 | W45: 0 | X45: 0 | Y45: 2345589.1 | Z45: 0.008692 | AA45: 0.9877 | AD45: 0.0088 | AG45: 0.0045 | AH45: 18 | AJ45: Liquidez diaria | AK45: S | AL45: 0.15 | AM45: N | AN45: N | AO45: AA+ | AP45: Banco Beta | AQ45: Custodiante Ficticio | AR45: CT-016 | AS45: D+0 | AT45: 0 | AU45: Autorizado | AW45: Financeiro | AX45: 45716 | AY45: Ativa | AZ45: APL-016-202502 | BA45: =ROUND(T45-(O45+P45-Q45-R45+S45-IF(AK45="S",U45+V45,0)),2) -> 0 | BB45: =(O45+T45)/2 -> 2336988.1
A46: 45716 | B46: APL-017 | C46: Recursos de Terceiros | D46: CC-004 | E46: Banco Epsilon | F46: CDB | G46: CDB Banco Epsilon | H46: CDI | I46: 0.9841 | K46: 45459 | L46: 45700 | M46: No vencimento | N46: Curto prazo | O46: 2221701.7 | P46: 0 | Q46: 0 | R46: 0 | S46: 19240.11 | T46: 2240941.8 | U46: 0 | V46: 0 | W46: 2886.02 | X46: 0 | Y46: 2238055.8 | Z46: 0.00866 | AA46: 0.9841 | AD46: 0.0088 | AG46: 0.0045 | AH46: 18 | AI46: -16 | AJ46: Ate 90 dias | AK46: N | AL46: 0.15 | AM46: N | AN46: S | AO46: AA+ | AP46: Banco Epsilon | AQ46: Custodiante Ficticio | AR46: CT-017 | AS46: No vencimento | AT46: 0 | AU46: Autorizado | AW46: Financeiro | AX46: 45716 | AY46: Ativa | AZ46: APL-017-202502 | BA46: =ROUND(T46-(O46+P46-Q46-R46+S46-IF(AK46="S",U46+V46,0)),2) -> 0 | BB46: =(O46+T46)/2 -> 2231321.8
A47: 45716 | B47: APL-018 | C47: Recursos Proprios | D47: CC-003 | E47: Banco Alfa | F47: LCA | G47: LCA Banco Alfa | H47: CDI | I47: 0.9262 | K47: 45642 | L47: 45925 | M47: No vencimento | N47: Curto prazo | O47: 2390630.7 | P47: 0 | Q47: 0 | R47: 0 | S47: 19484.98 | T47: 2410115.7 | U47: 0 | V47: 0 | W47: 0 | X47: 0 | Y47: 2410115.7 | Z47: 0.008151 | AA47: 0.9262 | AD47: 0.0088 | AG47: 0.0045 | AH47: 18 | AI47: 209 | AJ47: 91 a 360 dias | AK47: N | AL47: 0 | AM47: S | AN47: S | AO47: AA | AP47: Banco Alfa | AQ47: Custodiante Ficticio | AR47: CT-018 | AS47: No vencimento | AT47: 0 | AU47: Autorizado | AW47: Financeiro | AX47: 45716 | AY47: Ativa | AZ47: APL-018-202502 | BA47: =ROUND(T47-(O47+P47-Q47-R47+S47-IF(AK47="S",U47+V47,0)),2) -> 0 | BB47: =(O47+T47)/2 -> 2400373.2
A48: 45716 | B48: APL-019 | C48: Financiamento de Base | D48: CC-004 | E48: Banco Gama | F48: LCI | G48: LCI Banco Gama | H48: CDI | I48: 0.9199 | K48: 45563 | L48: 47306 | M48: No vencimento | N48: Longo prazo | O48: 1036510.8 | P48: 0 | Q48: 0 | R48: 0 | S48: 8390.68 | T48: 1044901.5 | U48: 0 | V48: 0 | W48: 0 | X48: 0 | Y48: 1044901.5 | Z48: 0.008095 | AA48: 0.9199 | AD48: 0.0088 | AG48: 0.0045 | AH48: 18 | AI48: 1590 | AJ48: Acima de 360 dias | AK48: N | AL48: 0 | AM48: S | AN48: S | AO48: AAA | AP48: Banco Gama | AQ48: Custodiante Ficticio | AR48: CT-019 | AS48: No vencimento | AT48: 0 | AU48: Autorizado | AW48: Financeiro | AX48: 45716 | AY48: Ativa | AZ48: APL-019-202502 | BA48: =ROUND(T48-(O48+P48-Q48-R48+S48-IF(AK48="S",U48+V48,0)),2) -> 0 | BB48: =(O48+T48)/2 -> 1040706.1
A49: 45716 | B49: APL-020 | C49: Recursos Proprios | D49: CC-006 | E49: Cooperativa Delta | F49: Tesouro Selic | G49: Tesouro Selic Cooperativa Delta | H49: CDI | I49: 0.9904 | K49: 45550 | L49: 45755 | M49: No vencimento | N49: Curto prazo | O49: 1420346.9 | P49: 291416.18 | Q49: 385388.38 | R49: 0 | S49: 11969.55 | T49: 1338344.3 | U49: 0 | V49: 0 | W49: 1795.43 | X49: 0 | Y49: 1336548.9 | Z49: 0.006993 | AA49: 0.7946 | AD49: 0.0088 | AG49: 0.0045 | AH49: 18 | AI49: 39 | AJ49: Ate 90 dias | AK49: N | AL49: 0.15 | AM49: N | AN49: N | AO49: AA+ | AP49: Cooperativa Delta | AQ49: Custodiante Ficticio | AR49: CT-020 | AS49: No vencimento | AT49: 0 | AU49: Autorizado | AW49: Financeiro | AX49: 45716 | AY49: Ativa | AZ49: APL-020-202502 | BA49: =ROUND(T49-(O49+P49-Q49-R49+S49-IF(AK49="S",U49+V49,0)),2) -> 0 | BB49: =(O49+T49)/2 -> 1379345.6
A50: 45716 | B50: APL-021 | C50: Financiamento de Base | D50: CC-001 | E50: Banco Alfa | F50: Fundo DI | G50: Fundo DI Banco Alfa | H50: CDI | I50: 0.9514 | K50: 45345 | M50: Diaria | N50: Curto prazo | O50: 2285705.2 | P50: 183005.66 | Q50: 0 | R50: 0 | S50: 19902.75 | T50: 2485628.2 | U50: 2985.41 | V50: 0 | W50: 0 | X50: 0 | Y50: 2485628.2 | Z50: 0.008062 | AA50: 0.9161 | AD50: 0.0088 | AG50: 0.0045 | AH50: 18 | AJ50: Liquidez diaria | AK50: S | AL50: 0.15 | AM50: N | AN50: N | AO50: AA+ | AP50: Banco Alfa | AQ50: Custodiante Ficticio | AR50: CT-021 | AS50: D+0 | AT50: 0 | AU50: Autorizado | AW50: Financeiro | AX50: 45716 | AY50: Ativa | AZ50: APL-021-202502 | BA50: =ROUND(T50-(O50+P50-Q50-R50+S50-IF(AK50="S",U50+V50,0)),2) -> 0 | BB50: =(O50+T50)/2 -> 2385666.7
A51: 45716 | B51: APL-022 | C51: Recursos Proprios | D51: CC-009 | E51: Banco Alfa | F51: Tesouro Selic | G51: Tesouro Selic Banco Alfa | H51: CDI | I51: 0.9926 | K51: 45543 | L51: 46707 | M51: No vencimento | N51: Longo prazo | O51: 2364094.3 | P51: 0 | Q51: 0 | R51: 0 | S51: 20650.08 | T51: 2384744.4 | U51: 0 | V51: 0 | W51: 3097.51 | X51: 0 | Y51: 2381646.9 | Z51: 0.008735 | AA51: 0.9926 | AD51: 0.0088 | AG51: 0.0045 | AH51: 18 | AI51: 991 | AJ51: Acima de 360 dias | AK51: N | AL51: 0.15 | AM51: N | AN51: N | AO51: AAA | AP51: Banco Alfa | AQ51: Custodiante Ficticio | AR51: CT-022 | AS51: No vencimento | AT51: 0 | AU51: Autorizado | AW51: Financeiro | AX51: 45716 | AY51: Ativa | AZ51: APL-022-202502 | BA51: =ROUND(T51-(O51+P51-Q51-R51+S51-IF(AK51="S",U51+V51,0)),2) -> 0 | BB51: =(O51+T51)/2 -> 2374419.4
A52: 45716 | B52: APL-023 | C52: Recursos de Terceiros | D52: CC-004 | E52: Banco Beta | F52: Compromissada | G52: Compromissada Banco Beta | H52: CDI | I52: 0.8094 | K52: 45530 | M52: Diaria | N52: Curto prazo | O52: 1677306.6 | P52: 0 | Q52: 0 | R52: 0 | S52: 11946.99 | T52: 1689253.6 | U52: 0 | V52: 0 | W52: 1792.05 | X52: 0 | Y52: 1687461.6 | Z52: 0.007123 | AA52: 0.8094 | AD52: 0.0088 | AG52: 0.0045 | AH52: 18 | AJ52: Liquidez diaria | AK52: N | AL52: 0.15 | AM52: N | AN52: N | AO52: AA+ | AP52: Banco Beta | AQ52: Custodiante Ficticio | AR52: CT-023 | AS52: D+0 | AT52: 0 | AU52: Autorizado | AW52: Financeiro | AX52: 45716 | AY52: Ativa | AZ52: APL-023-202502 | BA52: =ROUND(T52-(O52+P52-Q52-R52+S52-IF(AK52="S",U52+V52,0)),2) -> 0 | BB52: =(O52+T52)/2 -> 1683280.1
A53: 45716 | B53: APL-024 | C53: Financiamento de Base | D53: CC-002 | E53: Cooperativa Delta | F53: Tesouro Selic | G53: Tesouro Selic Cooperativa Delta | H53: CDI | I53: 0.9912 | K53: 45488 | L53: 45982 | M53: No vencimento | N53: Curto prazo | O53: 1851394.1 | P53: 136456.68 | Q53: 0 | R53: 0 | S53: 16744.02 | T53: 2004594.8 | U53: 0 | V53: 0 | W53: 2511.6 | X53: 0 | Y53: 2002083.2 | Z53: 0.008423 | AA53: 0.9572 | AD53: 0.0088 | AG53: 0.0045 | AH53: 18 | AI53: 266 | AJ53: 91 a 360 dias | AK53: N | AL53: 0.15 | AM53: N | AN53: N | AO53: AA | AP53: Cooperativa Delta | AQ53: Custodiante Ficticio | AR53: CT-024 | AS53: No vencimento | AT53: 0 | AU53: Autorizado | AW53: Financeiro | AX53: 45716 | AY53: Ativa | AZ53: APL-024-202502 | BA53: =ROUND(T53-(O53+P53-Q53-R53+S53-IF(AK53="S",U53+V53,0)),2) -> 0 | BB53: =(O53+T53)/2 -> 1927994.5
A54: 45716 | B54: APL-025 | C54: Recursos de Terceiros | D54: CC-003 | E54: Banco Beta | F54: LCA | G54: LCA Banco Beta | H54: CDI | I54: 0.8995 | K54: 45389 | L54: 47335 | M54: No vencimento | N54: Longo prazo | O54: 801087.51 | P54: 0 | Q54: 0 | R54: 0 | S54: 6341.09 | T54: 807428.6 | U54: 0 | V54: 0 | W54: 0 | X54: 0 | Y54: 807428.6 | Z54: 0.007916 | AA54: 0.8995 | AD54: 0.0088 | AG54: 0.0045 | AH54: 18 | AI54: 1619 | AJ54: Acima de 360 dias | AK54: N | AL54: 0 | AM54: S | AN54: S | AO54: AA | AP54: Banco Beta | AQ54: Custodiante Ficticio | AR54: CT-025 | AS54: No vencimento | AT54: 0 | AU54: Autorizado | AW54: Financeiro | AX54: 45716 | AY54: Ativa | AZ54: APL-025-202502 | BA54: =ROUND(T54-(O54+P54-Q54-R54+S54-IF(AK54="S",U54+V54,0)),2) -> 0 | BB54: =(O54+T54)/2 -> 804258.05
A55: 45716 | B55: APL-026 | C55: Recursos Proprios | D55: CC-002 | E55: Cooperativa Delta | F55: LCA | G55: LCA Cooperativa Delta | H55: CDI | I55: 0.9448 | K55: 45539 | L55: 45979 | M55: No vencimento | N55: Curto prazo | O55: 1754535.4 | P55: 0 | Q55: 0 | R55: 0 | S55: 14587.63 | T55: 1769123 | U55: 0 | V55: 0 | W55: 0 | X55: 0 | Y55: 1769123 | Z55: 0.008314 | AA55: 0.9448 | AD55: 0.0088 | AG55: 0.0045 | AH55: 18 | AI55: 263 | AJ55: 91 a 360 dias | AK55: N | AL55: 0 | AM55: S | AN55: S | AO55: AAA | AP55: Cooperativa Delta | AQ55: Custodiante Ficticio | AR55: CT-026 | AS55: No vencimento | AT55: 0 | AU55: Autorizado | AW55: Financeiro | AX55: 45716 | AY55: Ativa | AZ55: APL-026-202502 | BA55: =ROUND(T55-(O55+P55-Q55-R55+S55-IF(AK55="S",U55+V55,0)),2) -> 0 | BB55: =(O55+T55)/2 -> 1761829.2
A56: 45716 | B56: APL-027 | C56: Recursos Proprios | D56: CC-007 | E56: Cooperativa Delta | F56: LCI | G56: LCI Cooperativa Delta | H56: CDI | I56: 0.8702 | K56: 45520 | L56: 46205 | M56: No vencimento | N56: Longo prazo | O56: 1014854.2 | P56: 0 | Q56: 0 | R56: 0 | S56: 7771.51 | T56: 1022625.7 | U56: 0 | V56: 0 | W56: 0 | X56: 0 | Y56: 1022625.7 | Z56: 0.007658 | AA56: 0.8702 | AD56: 0.0088 | AG56: 0.0045 | AH56: 18 | AI56: 489 | AJ56: Acima de 360 dias | AK56: N | AL56: 0 | AM56: S | AN56: S | AO56: AA | AP56: Cooperativa Delta | AQ56: Custodiante Ficticio | AR56: CT-027 | AS56: No vencimento | AT56: 0 | AU56: Autorizado | AW56: Financeiro | AX56: 45716 | AY56: Ativa | AZ56: APL-027-202502 | BA56: =ROUND(T56-(O56+P56-Q56-R56+S56-IF(AK56="S",U56+V56,0)),2) -> 0 | BB56: =(O56+T56)/2 -> 1018740
A57: 45716 | B57: APL-028 | C57: Financiamento de Base | D57: CC-009 | E57: Banco Gama | F57: Compromissada | G57: Compromissada Banco Gama | H57: CDI | I57: 0.8662 | K57: 45496 | M57: Diaria | N57: Curto prazo | O57: 872440.62 | P57: 0 | Q57: 0 | R57: 0 | S57: 6650.23 | T57: 879090.85 | U57: 0 | V57: 0 | W57: 997.53 | X57: 0 | Y57: 878093.32 | Z57: 0.007623 | AA57: 0.8662 | AD57: 0.0088 | AG57: 0.0045 | AH57: 18 | AJ57: Liquidez diaria | AK57: N | AL57: 0.15 | AM57: N | AN57: N | AO57: AA | AP57: Banco Gama | AQ57: Custodiante Ficticio | AR57: CT-028 | AS57: D+0 | AT57: 0 | AU57: Autorizado | AW57: Financeiro | AX57: 45716 | AY57: Ativa | AZ57: APL-028-202502 | BA57: =ROUND(T57-(O57+P57-Q57-R57+S57-IF(AK57="S",U57+V57,0)),2) -> 0 | BB57: =(O57+T57)/2 -> 875765.73
A58: 45747 | B58: APL-001 | C58: Financiamento de Base | D58: CC-002 | E58: Banco Alfa | F58: LCA | G58: LCA Banco Alfa | H58: CDI | I58: 0.9274 | K58: 45635 | L58: 46117 | M58: No vencimento | N58: Longo prazo | O58: 2273946.1 | P58: 0 | Q58: 0 | R58: 0 | S58: 20455.92 | T58: 2294402 | U58: 0 | V58: 0 | W58: 0 | X58: 0 | Y58: 2294402 | Z58: 0.008996 | AA58: 0.9274 | AD58: 0.0097 | AG58: -0.001 | AH58: 21 | AI58: 370 | AJ58: Acima de 360 dias | AK58: N | AL58: 0 | AM58: S | AN58: S | AO58: AA | AP58: Banco Alfa | AQ58: Custodiante Ficticio | AR58: CT-001 | AS58: No vencimento | AT58: 0 | AU58: Autorizado | AW58: Financeiro | AX58: 45747 | AY58: Ativa | AZ58: APL-001-202503 | BA58: =ROUND(T58-(O58+P58-Q58-R58+S58-IF(AK58="S",U58+V58,0)),2) -> 0 | BB58: =(O58+T58)/2 -> 2284174
A59: 45747 | B59: APL-002 | C59: Recursos Proprios | D59: CC-009 | E59: Banco Epsilon | F59: LCA | G59: LCA Banco Epsilon | H59: CDI | I59: 0.9221 | K59: 45475 | L59: 45695 | M59: No vencimento | N59: Curto prazo | O59: 1389252.6 | P59: 0 | Q59: 0 | R59: 0 | S59: 12425.99 | T59: 1401678.6 | U59: 0 | V59: 0 | W59: 0 | X59: 0 | Y59: 1401678.6 | Z59: 0.008944 | AA59: 0.9221 | AD59: 0.0097 | AG59: -0.001 | AH59: 21 | AI59: -52 | AJ59: Ate 90 dias | AK59: N | AL59: 0 | AM59: S | AN59: S | AO59: AA+ | AP59: Banco Epsilon | AQ59: Custodiante Ficticio | AR59: CT-002 | AS59: No vencimento | AT59: 0 | AU59: Autorizado | AW59: Financeiro | AX59: 45747 | AY59: Ativa | AZ59: APL-002-202503 | BA59: =ROUND(T59-(O59+P59-Q59-R59+S59-IF(AK59="S",U59+V59,0)),2) -> 0 | BB59: =(O59+T59)/2 -> 1395465.6
A60: 45747 | B60: APL-003 | C60: Recursos Proprios | D60: CC-007 | E60: Banco Beta | F60: Tesouro IPCA+ | G60: Tesouro IPCA+ Banco Beta | H60: IPCA | J60: 0.0048 | K60: 45523 | L60: 46412 | M60: No vencimento | N60: Longo prazo | O60: 231085.06 | P60: 0 | Q60: 231085.06 | R60: 0 | S60: 439.06 | T60: 439.06 | U60: 0 | V60: 0 | W60: 65.86 | X60: 0 | Y60: 373.2 | Z60: 0.0019 | AA60: 0.1959 | AD60: 0.0097 | AG60: -0.001 | AH60: 21 | AI60: 665 | AJ60: Acima de 360 dias | AK60: N | AL60: 0.15 | AM60: N | AN60: N | AO60: AA+ | AP60: Banco Beta | AQ60: Custodiante Ficticio | AR60: CT-003 | AS60: No vencimento | AT60: 0 | AU60: Autorizado | AW60: Financeiro | AX60: 45747 | AY60: Ativa | AZ60: APL-003-202503 | BA60: =ROUND(T60-(O60+P60-Q60-R60+S60-IF(AK60="S",U60+V60,0)),2) -> 0 | BB60: =(O60+T60)/2 -> 115762.06
A61: 45747 | B61: APL-004 | C61: Recursos de Terceiros | D61: CC-005 | E61: Banco Alfa | F61: Tesouro Selic | G61: Tesouro Selic Banco Alfa | H61: CDI | I61: 1.0061 | K61: 45335 | L61: 45836 | M61: No vencimento | N61: Curto prazo | O61: 1871836.1 | P61: 0 | Q61: 0 | R61: 0 | S61: 18267.57 | T61: 1890103.7 | U61: 0 | V61: 0 | W61: 2740.14 | X61: 0 | Y61: 1887363.5 | Z61: 0.009759 | AA61: 1.0061 | AD61: 0.0097 | AG61: -0.001 | AH61: 21 | AI61: 89 | AJ61: Ate 90 dias | AK61: N | AL61: 0.15 | AM61: N | AN61: N | AO61: AA | AP61: Banco Alfa | AQ61: Custodiante Ficticio | AR61: CT-004 | AS61: No vencimento | AT61: 0 | AU61: Autorizado | AW61: Financeiro | AX61: 45747 | AY61: Ativa | AZ61: APL-004-202503 | BA61: =ROUND(T61-(O61+P61-Q61-R61+S61-IF(AK61="S",U61+V61,0)),2) -> 0 | BB61: =(O61+T61)/2 -> 1880969.9
A62: 45747 | B62: APL-005 | C62: Recursos de Terceiros | D62: CC-004 | E62: Cooperativa Delta | F62: LCA | G62: LCA Cooperativa Delta | H62: CDI | I62: 0.9293 | K62: 45340 | L62: 46711 | M62: No vencimento | N62: Longo prazo | O62: 128075.32 | P62: 0 | Q62: 0 | R62: 0 | S62: 1154.5 | T62: 129229.82 | U62: 0 | V62: 0 | W62: 0 | X62: 0 | Y62: 129229.82 | Z62: 0.009014 | AA62: 0.9293 | AD62: 0.0097 | AG62: -0.001 | AH62: 21 | AI62: 964 | AJ62: Acima de 360 dias | AK62: N | AL62: 0 | AM62: S | AN62: S | AO62: AAA | AP62: Cooperativa Delta | AQ62: Custodiante Ficticio | AR62: CT-005 | AS62: No vencimento | AT62: 0 | AU62: Autorizado | AW62: Financeiro | AX62: 45747 | AY62: Ativa | AZ62: APL-005-202503 | BA62: =ROUND(T62-(O62+P62-Q62-R62+S62-IF(AK62="S",U62+V62,0)),2) -> 0 | BB62: =(O62+T62)/2 -> 128652.57
A63: 45747 | B63: APL-006 | C63: Recursos Proprios | D63: CC-002 | E63: Banco Gama | F63: Fundo DI | G63: Fundo DI Banco Gama | H63: CDI | I63: 0.959 | K63: 45350 | M63: Diaria | N63: Curto prazo | O63: 1178236.5 | P63: 0 | Q63: 0 | R63: 0 | S63: 10960.31 | T63: 1187552.7 | U63: 1644.05 | V63: 0 | W63: 0 | X63: 0 | Y63: 1187552.7 | Z63: 0.009302 | AA63: 0.959 | AD63: 0.0097 | AG63: -0.001 | AH63: 21 | AJ63: Liquidez diaria | AK63: S | AL63: 0.15 | AM63: N | AN63: N | AO63: AA | AP63: Banco Gama | AQ63: Custodiante Ficticio | AR63: CT-006 | AS63: D+0 | AT63: 0 | AU63: Autorizado | AW63: Financeiro | AX63: 45747 | AY63: Ativa | AZ63: APL-006-202503 | BA63: =ROUND(T63-(O63+P63-Q63-R63+S63-IF(AK63="S",U63+V63,0)),2) -> 0 | BB63: =(O63+T63)/2 -> 1182894.6
A64: 45747 | B64: APL-007 | C64: Financiamento de Base | D64: CC-002 | E64: Banco Beta | F64: Tesouro Selic | G64: Tesouro Selic Banco Beta | H64: CDI | I64: 1.0022 | K64: 45455 | L64: 46335 | M64: No vencimento | N64: Longo prazo | O64: 477935.99 | P64: 0 | Q64: 0 | R64: 0 | S64: 4646.18 | T64: 482582.17 | U64: 0 | V64: 0 | W64: 696.93 | X64: 0 | Y64: 481885.24 | Z64: 0.009721 | AA64: 1.0022 | AD64: 0.0097 | AG64: -0.001 | AH64: 21 | AI64: 588 | AJ64: Acima de 360 dias | AK64: N | AL64: 0.15 | AM64: N | AN64: N | AO64: AA+ | AP64: Banco Beta | AQ64: Custodiante Ficticio | AR64: CT-007 | AS64: No vencimento | AT64: 0 | AU64: Autorizado | AW64: Financeiro | AX64: 45747 | AY64: Ativa | AZ64: APL-007-202503 | BA64: =ROUND(T64-(O64+P64-Q64-R64+S64-IF(AK64="S",U64+V64,0)),2) -> 0 | BB64: =(O64+T64)/2 -> 480259.08
A65: 45747 | B65: APL-008 | C65: Recursos de Terceiros | D65: CC-009 | E65: Banco Beta | F65: Fundo DI | G65: Fundo DI Banco Beta | H65: CDI | I65: 0.951 | K65: 45517 | M65: Diaria | N65: Curto prazo | O65: 1059872.6 | P65: 0 | Q65: 0 | R65: 0 | S65: 9777.01 | T65: 1068183 | U65: 1466.55 | V65: 0 | W65: 0 | X65: 0 | Y65: 1068183 | Z65: 0.009225 | AA65: 0.951 | AD65: 0.0097 | AG65: -0.001 | AH65: 21 | AJ65: Liquidez diaria | AK65: S | AL65: 0.15 | AM65: N | AN65: N | AO65: AA+ | AP65: Banco Beta | AQ65: Custodiante Ficticio | AR65: CT-008 | AS65: D+0 | AT65: 0 | AU65: Autorizado | AW65: Financeiro | AX65: 45747 | AY65: Ativa | AZ65: APL-008-202503 | BA65: =ROUND(T65-(O65+P65-Q65-R65+S65-IF(AK65="S",U65+V65,0)),2) -> 0 | BB65: =(O65+T65)/2 -> 1064027.8
A66: 45747 | B66: APL-009 | C66: Recursos Proprios | D66: CC-004 | E66: Banco Beta | F66: CDB | G66: CDB Banco Beta | H66: CDI | I66: 1.0439 | K66: 45317 | L66: 46577 | M66: No vencimento | N66: Longo prazo | O66: 1168597.8 | P66: 0 | Q66: 0 | R66: 0 | S66: 11833.02 | T66: 1180430.8 | U66: 0 | V66: 0 | W66: 1774.95 | X66: 0 | Y66: 1178655.9 | Z66: 0.010126 | AA66: 1.0439 | AD66: 0.0097 | AG66: -0.001 | AH66: 21 | AI66: 830 | AJ66: Acima de 360 dias | AK66: N | AL66: 0.15 | AM66: N | AN66: S | AO66: AA | AP66: Banco Beta | AQ66: Custodiante Ficticio | AR66: CT-009 | AS66: No vencimento | AT66: 0 | AU66: Autorizado | AW66: Financeiro | AX66: 45747 | AY66: Ativa | AZ66: APL-009-202503 | BA66: =ROUND(T66-(O66+P66-Q66-R66+S66-IF(AK66="S",U66+V66,0)),2) -> 0 | BB66: =(O66+T66)/2 -> 1174514.3
A67: 45747 | B67: APL-010 | C67: Recursos Proprios | D67: CC-005 | E67: Banco Beta | F67: Tesouro Selic | G67: Tesouro Selic Banco Beta | H67: CDI | I67: 0.9928 | K67: 45612 | L67: 47072 | M67: No vencimento | N67: Longo prazo | O67: 1909447 | P67: 0 | Q67: 211026.28 | R67: 0 | S67: 17372.17 | T67: 1715792.9 | U67: 0 | V67: 0 | W67: 2605.83 | X67: 0 | Y67: 1713187.1 | Z67: 0.009098 | AA67: 0.9379 | AD67: 0.0097 | AG67: -0.001 | AH67: 21 | AI67: 1325 | AJ67: Acima de 360 dias | AK67: N | AL67: 0.15 | AM67: N | AN67: N | AO67: AA | AP67: Banco Beta | AQ67: Custodiante Ficticio | AR67: CT-010 | AS67: No vencimento | AT67: 0 | AU67: Autorizado | AW67: Financeiro | AX67: 45747 | AY67: Ativa | AZ67: APL-010-202503 | BA67: =ROUND(T67-(O67+P67-Q67-R67+S67-IF(AK67="S",U67+V67,0)),2) -> 0 | BB67: =(O67+T67)/2 -> 1812620
A68: 45747 | B68: APL-011 | C68: Recursos de Terceiros | D68: CC-006 | E68: Banco Epsilon | F68: Fundo Aplic. Automatica | G68: Fundo Aplic. Automatica Banco Epsilon | H68: CDI | I68: 0.2329 | K68: 45492 | M68: Diaria | N68: Curto prazo | O68: 2503010.4 | P68: 0 | Q68: 381279.87 | R68: 0 | S68: 5223.95 | T68: 2126170.9 | U68: 783.59 | V68: 0 | W68: 0 | X68: 0 | Y68: 2126170.9 | Z68: 0.002087 | AA68: 0.2152 | AD68: 0.0097 | AG68: -0.001 | AH68: 21 | AJ68: Liquidez diaria | AK68: S | AL68: 0.15 | AM68: N | AN68: N | AO68: AAA | AP68: Banco Epsilon | AQ68: Custodiante Ficticio | AR68: CT-011 | AS68: D+0 | AT68: 0 | AU68: Autorizado | AW68: Financeiro | AX68: 45747 | AY68: Ativa | AZ68: APL-011-202503 | BA68: =ROUND(T68-(O68+P68-Q68-R68+S68-IF(AK68="S",U68+V68,0)),2) -> 0 | BB68: =(O68+T68)/2 -> 2314590.6
A69: 45747 | B69: APL-012 | C69: Recursos Proprios | D69: CC-003 | E69: Banco Alfa | F69: Compromissada | G69: Compromissada Banco Alfa | H69: CDI | I69: 0.8627 | K69: 45319 | M69: Diaria | N69: Curto prazo | O69: 2022144.6 | P69: 0 | Q69: 0 | R69: 0 | S69: 16921.69 | T69: 2039066.3 | U69: 0 | V69: 0 | W69: 2538.25 | X69: 0 | Y69: 2036528.1 | Z69: 0.008368 | AA69: 0.8627 | AD69: 0.0097 | AG69: -0.001 | AH69: 21 | AJ69: Liquidez diaria | AK69: N | AL69: 0.15 | AM69: N | AN69: N | AO69: AAA | AP69: Banco Alfa | AQ69: Custodiante Ficticio | AR69: CT-012 | AS69: D+0 | AT69: 0 | AU69: Autorizado | AW69: Financeiro | AX69: 45747 | AY69: Ativa | AZ69: APL-012-202503 | BA69: =ROUND(T69-(O69+P69-Q69-R69+S69-IF(AK69="S",U69+V69,0)),2) -> 0 | BB69: =(O69+T69)/2 -> 2030605.5
A70: 45747 | B70: APL-013 | C70: Financiamento de Base | D70: CC-005 | E70: Banco Epsilon | F70: Tesouro IPCA+ | G70: Tesouro IPCA+ Banco Epsilon | H70: IPCA | J70: 0.0055 | K70: 45335 | L70: 47041 | M70: No vencimento | N70: Longo prazo | O70: 2155423.6 | P70: 23401.98 | Q70: 0 | R70: 0 | S70: 9752.06 | T70: 2188577.7 | U70: 0 | V70: 0 | W70: 1462.81 | X70: 0 | Y70: 2187114.9 | Z70: 0.004476 | AA70: 0.4614 | AD70: 0.0097 | AG70: -0.001 | AH70: 21 | AI70: 1294 | AJ70: Acima de 360 dias | AK70: N | AL70: 0.15 | AM70: N | AN70: N | AO70: AA | AP70: Banco Epsilon | AQ70: Custodiante Ficticio | AR70: CT-013 | AS70: No vencimento | AT70: 0 | AU70: Autorizado | AW70: Financeiro | AX70: 45747 | AY70: Ativa | AZ70: APL-013-202503 | BA70: =ROUND(T70-(O70+P70-Q70-R70+S70-IF(AK70="S",U70+V70,0)),2) -> 0 | BB70: =(O70+T70)/2 -> 2172000.6
A71: 45747 | B71: APL-014 | C71: Recursos Proprios | D71: CC-005 | E71: Banco Alfa | F71: CDB | G71: CDB Banco Alfa | H71: CDI | I71: 1.0104 | K71: 45614 | L71: 46702 | M71: No vencimento | N71: Longo prazo | O71: 1256002 | P71: 0 | Q71: 171631.99 | R71: 0 | S71: 11468.85 | T71: 1095838.9 | U71: 0 | V71: 0 | W71: 1720.33 | X71: 0 | Y71: 1094118.6 | Z71: 0.009131 | AA71: 0.9414 | AD71: 0.0097 | AG71: -0.001 | AH71: 21 | AI71: 955 | AJ71: Acima de 360 dias | AK71: N | AL71: 0.15 | AM71: N | AN71: S | AO71: AA | AP71: Banco Alfa | AQ71: Custodiante Ficticio | AR71: CT-014 | AS71: No vencimento | AT71: 0 | AU71: Autorizado | AW71: Financeiro | AX71: 45747 | AY71: Ativa | AZ71: APL-014-202503 | BA71: =ROUND(T71-(O71+P71-Q71-R71+S71-IF(AK71="S",U71+V71,0)),2) -> 0 | BB71: =(O71+T71)/2 -> 1175920.5
A72: 45747 | B72: APL-015 | C72: Recursos Proprios | D72: CC-005 | E72: Banco Epsilon | F72: Fundo Aplic. Automatica | G72: Fundo Aplic. Automatica Banco Epsilon | H72: CDI | I72: 0.3263 | K72: 45368 | M72: Diaria | N72: Curto prazo | O72: 1300349.1 | P72: 0 | Q72: 0 | R72: 0 | S72: 4115.75 | T72: 1303847.4 | U72: 617.36 | V72: 0 | W72: 0 | X72: 0 | Y72: 1303847.4 | Z72: 0.003165 | AA72: 0.3263 | AD72: 0.0097 | AG72: -0.001 | AH72: 21 | AJ72: Liquidez diaria | AK72: S | AL72: 0.15 | AM72: N | AN72: N | AO72: AA+ | AP72: Banco Epsilon | AQ72: Custodiante Ficticio | AR72: CT-015 | AS72: D+0 | AT72: 0 | AU72: Autorizado | AW72: Financeiro | AX72: 45747 | AY72: Ativa | AZ72: APL-015-202503 | BA72: =ROUND(T72-(O72+P72-Q72-R72+S72-IF(AK72="S",U72+V72,0)),2) -> 0 | BB72: =(O72+T72)/2 -> 1302098.2
A73: 45747 | B73: APL-016 | C73: Recursos Proprios | D73: CC-009 | E73: Banco Beta | F73: Fundo DI | G73: Fundo DI Banco Beta | H73: CDI | I73: 0.9877 | K73: 45468 | M73: Diaria | N73: Curto prazo | O73: 2345589.1 | P73: 0 | Q73: 0 | R73: 0 | S73: 22472.36 | T73: 2364690.6 | U73: 3370.85 | V73: 0 | W73: 0 | X73: 0 | Y73: 2364690.6 | Z73: 0.009581 | AA73: 0.9877 | AD73: 0.0097 | AG73: -0.001 | AH73: 21 | AJ73: Liquidez diaria | AK73: S | AL73: 0.15 | AM73: N | AN73: N | AO73: AA | AP73: Banco Beta | AQ73: Custodiante Ficticio | AR73: CT-016 | AS73: D+0 | AT73: 0 | AU73: Autorizado | AW73: Financeiro | AX73: 45747 | AY73: Ativa | AZ73: APL-016-202503 | BA73: =ROUND(T73-(O73+P73-Q73-R73+S73-IF(AK73="S",U73+V73,0)),2) -> 0 | BB73: =(O73+T73)/2 -> 2355139.9
A74: 45747 | B74: APL-017 | C74: Recursos de Terceiros | D74: CC-004 | E74: Banco Epsilon | F74: CDB | G74: CDB Banco Epsilon | H74: CDI | I74: 0.9841 | K74: 45459 | L74: 45700 | M74: No vencimento | N74: Curto prazo | O74: 2240941.8 | P74: 0 | Q74: 0 | R74: 0 | S74: 21391.52 | T74: 2262333.3 | U74: 0 | V74: 0 | W74: 3208.73 | X74: 0 | Y74: 2259124.6 | Z74: 0.009546 | AA74: 0.9841 | AD74: 0.0097 | AG74: -0.001 | AH74: 21 | AI74: -47 | AJ74: Ate 90 dias | AK74: N | AL74: 0.15 | AM74: N | AN74: S | AO74: AAA | AP74: Banco Epsilon | AQ74: Custodiante Ficticio | AR74: CT-017 | AS74: No vencimento | AT74: 0 | AU74: Autorizado | AW74: Financeiro | AX74: 45747 | AY74: Ativa | AZ74: APL-017-202503 | BA74: =ROUND(T74-(O74+P74-Q74-R74+S74-IF(AK74="S",U74+V74,0)),2) -> 0 | BB74: =(O74+T74)/2 -> 2251637.6
A75: 45747 | B75: APL-018 | C75: Recursos Proprios | D75: CC-003 | E75: Banco Alfa | F75: LCA | G75: LCA Banco Alfa | H75: CDI | I75: 0.9262 | K75: 45642 | L75: 45925 | M75: No vencimento | N75: Curto prazo | O75: 2410115.7 | P75: 0 | Q75: 0 | R75: 0 | S75: 21652.82 | T75: 2431768.5 | U75: 0 | V75: 0 | W75: 0 | X75: 0 | Y75: 2431768.5 | Z75: 0.008984 | AA75: 0.9262 | AD75: 0.0097 | AG75: -0.001 | AH75: 21 | AI75: 178 | AJ75: 91 a 360 dias | AK75: N | AL75: 0 | AM75: S | AN75: S | AO75: AA | AP75: Banco Alfa | AQ75: Custodiante Ficticio | AR75: CT-018 | AS75: No vencimento | AT75: 0 | AU75: Autorizado | AW75: Financeiro | AX75: 45747 | AY75: Ativa | AZ75: APL-018-202503 | BA75: =ROUND(T75-(O75+P75-Q75-R75+S75-IF(AK75="S",U75+V75,0)),2) -> 0 | BB75: =(O75+T75)/2 -> 2420942.1
A76: 45747 | B76: APL-019 | C76: Financiamento de Base | D76: CC-004 | E76: Banco Gama | F76: LCI | G76: LCI Banco Gama | H76: CDI | I76: 0.9199 | K76: 45563 | L76: 47306 | M76: No vencimento | N76: Longo prazo | O76: 1044901.5 | P76: 0 | Q76: 107187.33 | R76: 0 | S76: 8845.47 | T76: 946559.6 | U76: 0 | V76: 0 | W76: 0 | X76: 0 | Y76: 946559.6 | Z76: 0.008465 | AA76: 0.8727 | AD76: 0.0097 | AG76: -0.001 | AH76: 21 | AI76: 1559 | AJ76: Acima de 360 dias | AK76: N | AL76: 0 | AM76: S | AN76: S | AO76: AAA | AP76: Banco Gama | AQ76: Custodiante Ficticio | AR76: CT-019 | AS76: No vencimento | AT76: 0 | AU76: Autorizado | AW76: Financeiro | AX76: 45747 | AY76: Ativa | AZ76: APL-019-202503 | BA76: =ROUND(T76-(O76+P76-Q76-R76+S76-IF(AK76="S",U76+V76,0)),2) -> 0 | BB76: =(O76+T76)/2 -> 995730.53
A77: 45747 | B77: APL-020 | C77: Recursos Proprios | D77: CC-006 | E77: Cooperativa Delta | F77: Tesouro Selic | G77: Tesouro Selic Cooperativa Delta | H77: CDI | I77: 0.9904 | K77: 45550 | L77: 45755 | M77: No vencimento | N77: Curto prazo | O77: 1338344.3 | P77: 0 | Q77: 0 | R77: 0 | S77: 12857.31 | T77: 1351201.6 | U77: 0 | V77: 0 | W77: 1928.6 | X77: 0 | Y77: 1349273 | Z77: 0.009607 | AA77: 0.9904 | AD77: 0.0097 | AG77: -0.001 | AH77: 21 | AI77: 8 | AJ77: Ate 90 dias | AK77: N | AL77: 0.15 | AM77: N | AN77: N | AO77: AA | AP77: Cooperativa Delta | AQ77: Custodiante Ficticio | AR77: CT-020 | AS77: No vencimento | AT77: 0 | AU77: Autorizado | AW77: Financeiro | AX77: 45747 | AY77: Ativa | AZ77: APL-020-202503 | BA77: =ROUND(T77-(O77+P77-Q77-R77+S77-IF(AK77="S",U77+V77,0)),2) -> 0 | BB77: =(O77+T77)/2 -> 1344772.9
A78: 45747 | B78: APL-021 | C78: Financiamento de Base | D78: CC-001 | E78: Banco Alfa | F78: Fundo DI | G78: Fundo DI Banco Alfa | H78: CDI | I78: 0.9514 | K78: 45345 | M78: Diaria | N78: Curto prazo | O78: 2485628.2 | P78: 0 | Q78: 0 | R78: 0 | S78: 22938.82 | T78: 2505126.2 | U78: 3440.82 | V78: 0 | W78: 0 | X78: 0 | Y78: 2505126.2 | Z78: 0.009229 | AA78: 0.9514 | AD78: 0.0097 | AG78: -0.001 | AH78: 21 | AJ78: Liquidez diaria | AK78: S | AL78: 0.15 | AM78: N | AN78: N | AO78: AA+ | AP78: Banco Alfa | AQ78: Custodiante Ficticio | AR78: CT-021 | AS78: D+0 | AT78: 0 | AU78: Autorizado | AW78: Financeiro | AX78: 45747 | AY78: Ativa | AZ78: APL-021-202503 | BA78: =ROUND(T78-(O78+P78-Q78-R78+S78-IF(AK78="S",U78+V78,0)),2) -> 0 | BB78: =(O78+T78)/2 -> 2495377.2
A79: 45747 | B79: APL-022 | C79: Recursos Proprios | D79: CC-009 | E79: Banco Alfa | F79: Tesouro Selic | G79: Tesouro Selic Banco Alfa | H79: CDI | I79: 0.9926 | K79: 45543 | L79: 46707 | M79: No vencimento | N79: Longo prazo | O79: 2384744.4 | P79: 0 | Q79: 0 | R79: 0 | S79: 22960.84 | T79: 2407705.3 | U79: 0 | V79: 0 | W79: 3444.13 | X79: 0 | Y79: 2404261.1 | Z79: 0.009628 | AA79: 0.9926 | AD79: 0.0097 | AG79: -0.001 | AH79: 21 | AI79: 960 | AJ79: Acima de 360 dias | AK79: N | AL79: 0.15 | AM79: N | AN79: N | AO79: AA | AP79: Banco Alfa | AQ79: Custodiante Ficticio | AR79: CT-022 | AS79: No vencimento | AT79: 0 | AU79: Autorizado | AW79: Financeiro | AX79: 45747 | AY79: Ativa | AZ79: APL-022-202503 | BA79: =ROUND(T79-(O79+P79-Q79-R79+S79-IF(AK79="S",U79+V79,0)),2) -> 0 | BB79: =(O79+T79)/2 -> 2396224.8
A80: 45747 | B80: APL-023 | C80: Recursos de Terceiros | D80: CC-004 | E80: Banco Beta | F80: Compromissada | G80: Compromissada Banco Beta | H80: CDI | I80: 0.8094 | K80: 45530 | M80: Diaria | N80: Curto prazo | O80: 1689253.6 | P80: 0 | Q80: 0 | R80: 0 | S80: 13262.63 | T80: 1702516.3 | U80: 0 | V80: 0 | W80: 1989.39 | X80: 0 | Y80: 1700526.9 | Z80: 0.007851 | AA80: 0.8094 | AD80: 0.0097 | AG80: -0.001 | AH80: 21 | AJ80: Liquidez diaria | AK80: N | AL80: 0.15 | AM80: N | AN80: N | AO80: AA+ | AP80: Banco Beta | AQ80: Custodiante Ficticio | AR80: CT-023 | AS80: D+0 | AT80: 0 | AU80: Autorizado | AW80: Financeiro | AX80: 45747 | AY80: Ativa | AZ80: APL-023-202503 | BA80: =ROUND(T80-(O80+P80-Q80-R80+S80-IF(AK80="S",U80+V80,0)),2) -> 0 | BB80: =(O80+T80)/2 -> 1695884.9
A81: 45747 | B81: APL-024 | C81: Financiamento de Base | D81: CC-002 | E81: Cooperativa Delta | F81: Tesouro Selic | G81: Tesouro Selic Cooperativa Delta | H81: CDI | I81: 0.9912 | K81: 45488 | L81: 45982 | M81: No vencimento | N81: Curto prazo | O81: 2004594.8 | P81: 0 | Q81: 0 | R81: 0 | S81: 19273.46 | T81: 2023868.3 | U81: 0 | V81: 0 | W81: 2891.02 | X81: 0 | Y81: 2020977.3 | Z81: 0.009615 | AA81: 0.9912 | AD81: 0.0097 | AG81: -0.001 | AH81: 21 | AI81: 235 | AJ81: 91 a 360 dias | AK81: N | AL81: 0.15 | AM81: N | AN81: N | AO81: AAA | AP81: Cooperativa Delta | AQ81: Custodiante Ficticio | AR81: CT-024 | AS81: No vencimento | AT81: 0 | AU81: Autorizado | AW81: Financeiro | AX81: 45747 | AY81: Ativa | AZ81: APL-024-202503 | BA81: =ROUND(T81-(O81+P81-Q81-R81+S81-IF(AK81="S",U81+V81,0)),2) -> 0 | BB81: =(O81+T81)/2 -> 2014231.6
A82: 45747 | B82: APL-025 | C82: Recursos de Terceiros | D82: CC-003 | E82: Banco Beta | F82: LCA | G82: LCA Banco Beta | H82: CDI | I82: 0.8995 | K82: 45389 | L82: 47335 | M82: No vencimento | N82: Longo prazo | O82: 807428.6 | P82: 0 | Q82: 0 | R82: 0 | S82: 7044.94 | T82: 814473.54 | U82: 0 | V82: 0 | W82: 0 | X82: 0 | Y82: 814473.54 | Z82: 0.008725 | AA82: 0.8995 | AD82: 0.0097 | AG82: -0.001 | AH82: 21 | AI82: 1588 | AJ82: Acima de 360 dias | AK82: N | AL82: 0 | AM82: S | AN82: S | AO82: AA+ | AP82: Banco Beta | AQ82: Custodiante Ficticio | AR82: CT-025 | AS82: No vencimento | AT82: 0 | AU82: Autorizado | AW82: Financeiro | AX82: 45747 | AY82: Ativa | AZ82: APL-025-202503 | BA82: =ROUND(T82-(O82+P82-Q82-R82+S82-IF(AK82="S",U82+V82,0)),2) -> 0 | BB82: =(O82+T82)/2 -> 810951.07
A83: 45747 | B83: APL-026 | C83: Recursos Proprios | D83: CC-002 | E83: Cooperativa Delta | F83: LCA | G83: LCA Cooperativa Delta | H83: CDI | I83: 0.9448 | K83: 45539 | L83: 45979 | M83: No vencimento | N83: Curto prazo | O83: 1769123 | P83: 0 | Q83: 0 | R83: 0 | S83: 16213.23 | T83: 1785336.2 | U83: 0 | V83: 0 | W83: 0 | X83: 0 | Y83: 1785336.2 | Z83: 0.009165 | AA83: 0.9448 | AD83: 0.0097 | AG83: -0.001 | AH83: 21 | AI83: 232 | AJ83: 91 a 360 dias | AK83: N | AL83: 0 | AM83: S | AN83: S | AO83: AA+ | AP83: Cooperativa Delta | AQ83: Custodiante Ficticio | AR83: CT-026 | AS83: No vencimento | AT83: 0 | AU83: Autorizado | AW83: Financeiro | AX83: 45747 | AY83: Ativa | AZ83: APL-026-202503 | BA83: =ROUND(T83-(O83+P83-Q83-R83+S83-IF(AK83="S",U83+V83,0)),2) -> 0 | BB83: =(O83+T83)/2 -> 1777229.6
A84: 45747 | B84: APL-027 | C84: Recursos Proprios | D84: CC-007 | E84: Cooperativa Delta | F84: LCI | G84: LCI Cooperativa Delta | H84: CDI | I84: 0.8702 | K84: 45520 | L84: 46205 | M84: No vencimento | N84: Longo prazo | O84: 1022625.7 | P84: 0 | Q84: 0 | R84: 0 | S84: 8631.92 | T84: 1031257.7 | U84: 0 | V84: 0 | W84: 0 | X84: 0 | Y84: 1031257.7 | Z84: 0.008441 | AA84: 0.8702 | AD84: 0.0097 | AG84: -0.001 | AH84: 21 | AI84: 458 | AJ84: Acima de 360 dias | AK84: N | AL84: 0 | AM84: S | AN84: S | AO84: AA | AP84: Cooperativa Delta | AQ84: Custodiante Ficticio | AR84: CT-027 | AS84: No vencimento | AT84: 0 | AU84: Autorizado | AW84: Financeiro | AX84: 45747 | AY84: Ativa | AZ84: APL-027-202503 | BA84: =ROUND(T84-(O84+P84-Q84-R84+S84-IF(AK84="S",U84+V84,0)),2) -> 0 | BB84: =(O84+T84)/2 -> 1026941.7
A85: 45747 | B85: APL-028 | C85: Financiamento de Base | D85: CC-009 | E85: Banco Gama | F85: Compromissada | G85: Compromissada Banco Gama | H85: CDI | I85: 0.8662 | K85: 45496 | M85: Diaria | N85: Curto prazo | O85: 879090.85 | P85: 0 | Q85: 0 | R85: 0 | S85: 7386.24 | T85: 886477.09 | U85: 0 | V85: 0 | W85: 1107.94 | X85: 0 | Y85: 885369.15 | Z85: 0.008402 | AA85: 0.8662 | AD85: 0.0097 | AG85: -0.001 | AH85: 21 | AJ85: Liquidez diaria | AK85: N | AL85: 0.15 | AM85: N | AN85: N | AO85: AA | AP85: Banco Gama | AQ85: Custodiante Ficticio | AR85: CT-028 | AS85: D+0 | AT85: 0 | AU85: Autorizado | AW85: Financeiro | AX85: 45747 | AY85: Ativa | AZ85: APL-028-202503 | BA85: =ROUND(T85-(O85+P85-Q85-R85+S85-IF(AK85="S",U85+V85,0)),2) -> 0 | BB85: =(O85+T85)/2 -> 882783.97

Sheet Config
A1: Parâmetros do relatório
A3: Mês de referência | B3: 45747 | C3: Atualizado pela macro ao importar. Pode ser alterado para rever meses anteriores.
A4: Limite de concentração por instituição | B4: 0.3 | C4: Parâmetro FICTÍCIO. Substitua pelo limite da sua política.
A5: Meta de rentabilidade (% do CDI) | B5: 1 | C5: Parâmetro FICTÍCIO.
A6: Tolerância de continuidade do saldo (R$) | B6: 1 | C6: Diferença aceitável entre saldo final anterior e saldo inicial atual.
A7: Pasta do PDF (vazio = pasta deste arquivo) | C7: Caminho local. Se o arquivo estiver em nuvem, a macro pergunta a pasta.
A8: Status do relatório | B8: FINAL | C8: Preenchido pela macro (FINAL ou PRELIMINAR). Não editar.
A9: Mês anterior (calculado) | B9: =EOMONTH(B3,-1) -> 45716

Sheet Cadastros
A1: Instituicao | C1: Modalidade | E1: Fonte | G1: Mes | I1: Novas instituições ou modalidades: acrescente uma linha na tabela correspondente (a conferência acusa ERRO até lá).
A2: Banco Alfa | C2: CDB | E2: Recursos Proprios | G2: 45688
A3: Banco Beta | C3: LCA | E3: Recursos de Terceiros | G3: 45716
A4: Banco Gama | C4: LCI | E4: Financiamento de Base | G4: 45747
A5: Cooperativa Delta | C5: Fundo DI
A6: Banco Epsilon | C6: Fundo Aplic. Automatica
C7: Tesouro Selic
C8: Tesouro IPCA+
C9: Compromissada

Sheet Indicadores
A1: Mes | B1: CDI_Mes | C1: IPCA_Mes | D1: Data_Base_Original | F1: Valores FICTÍCIOS, gravados pela macro a partir das colunas CDI_Mes e IPCA_Mes da planilha mensal.
A2: 45688 | B2: 0.0095 | C2: 0.003 | D2: 45688
A3: 45716 | B3: 0.0088 | C3: 0.0045 | D3: 45716
A4: 45747 | B4: 0.0097 | C4: -0.001 | D4: 45747

Sheet Log
A1: Data_Hora | B1: Usuario | C1: Arquivo | D1: Mes_Ref | E1: Linhas | F1: Data_Base_Original | G1: Observacao
B2: script | C2: construir_base.py | D2: 45747 | E2: 84 | G2: Carga inicial de exemplo (jan-mar/2025, dados fictícios)
